Workbook

Sheet Results
A1: Authors | B1: Author full names | C1: Author(s) ID | D1: Title | E1: Year | F1: Source title | G1: Volume | H1: Issue | I1: Art. No. | J1: Page start | K1: Page end | L1: Cited by | M1: DOI | N1: Link | O1: Abstract | P1: Author Keywords | Q1: Index Keywords | R1: Document Type | S1: Publication Stage | T1: Open Access | U1: Source | V1: EID
A2: Ton K. | B2: Ton, Karen (57213145412) | C2: 57213145412 | D2: Do Shared Auditors Improve Audit Quality? Evidence from Banking Relationships | E2: 2023 | F2: Accounting Review | G2: 98 | H2: 1 | J2: 423 | K2: 451 | L2: 17 | M2: 10.2308/TAR-2017-0179 | N2: https://www.scopus.com/inward/record.uri?eid=2-s2.0-85168957043&doi=10.2308%2FTAR-2017-0179&partnerID=40&md5=35ea053474f56ceb694d5a8a7755d047 | O2: Auditor knowledge is a key element in explaining the supply of audit quality, yet understanding of the drivers of this knowledge in the archival literature is limited. This study uses an archival approach to examine whether the sharing of auditors among firms in banking relationships results in information transfers that improve audit quality. I find that audit quality improves for both borrowers and lenders who share the same auditor office. Specifically, lenders who share an auditor office with their borrowers have more accurate loan-loss provisions, especially lenders with smaller commercial loan portfolios. Borrowers who share an auditor office with their lender are less likely to receive a clean audit opinion just prior to bankruptcy. Overall, these findings are consistent with shared auditors in banking relationships developing client specific knowledge that is transferable across clients and industries. © 2023 American Accounting Association. All rights reserved. | P2: audit quality; banking relationship; information transfer; shared auditors | R2: Article | S2: Final | U2: Scopus | V2: 2-s2.0-85168957043
A3: Tan H.-T.; Yeo F. | B3: Tan, Hun-Tong (7403011560); Yeo, Feng (57211460987) | C3: 7403011560; 57211460987 | D3: What Happens When Managers Are Informed? Effects of Critical Audit Matter Awareness and Auditor Relationship on Managers’ Accounting Estimates | E3: 2022 | F3: Accounting Review | G3: 97 | H3: 4 | J3: 399 | K3: 416 | L3: 20 | M3: 10.2308/TAR-2019-0370 | N3: https://www.scopus.com/inward/record.uri?eid=2-s2.0-85161047737&doi=10.2308%2FTAR-2019-0370&partnerID=40&md5=0d5b91735f149d78a73f6b9c9f8bcd50 | O3: We examine how managers’ accounting estimates are affected by whether they are informed about an impending critical audit matter (CAM) disclosure from a close or distant auditor. A close (distant) auditor is one who has a smaller (greater) social distance from the client in terms of their working relationship. We predict and find that being informed about an impending CAM by a close (distant) auditor leads to more (less) aggressive estimates than if managers are not informed. With a close auditor-client relationship, managers perceive a CAM disclosure as forewarning investors about estimate subjectivity, thus providing a moral license to report more aggressively. With a distant relationship, a CAM disclosure does not provide a moral license, but signals greater auditor scrutiny, which leads to less aggressive reporting. Our results inform regulators and standard setters about the effects of CAM on managers’ reporting decisions in the presence of a close auditor-client relationship. © 2022 American Accounting Association. All rights reserved. | P3: aggressive reporting; auditor-client working relationship; impending critical audit matters; moral licensing | R3: Article | S3: Final | U3: Scopus | V3: 2-s2.0-85161047737
A4: Lyle M.R.; Yohn T.L. | B4: Lyle, Matthew R. (26646633200); Yohn, Teri Lombardi (6508176752) | C4: 26646633200; 6508176752 | D4: Fundamental Analysis and Mean-Variance Optimal Portfolios | E4: 2022 | F4: Accounting Review | G4: 96 | H4: 6 | J4: 303 | K4: 327 | L4: 11 | M4: 10.2308/TAR-2019-0622 | N4: https://www.scopus.com/inward/record.uri?eid=2-s2.0-85132667755&doi=10.2308%2FTAR-2019-0622&partnerID=40&md5=0f6d7246db68c79a72ac488bf3a3a8e0 | O4: We integrate fundamental analysis with mean-variance portfolio optimization to form fully optimized fundamental portfolios. We find that fully optimized fundamental portfolios produce large out-of-sample factor alphas with high Sharpe ratios. They substantially outperform equal-weighted and value-weighted portfolios of stocks in the extreme decile of expected returns, an approach commonly used in fundamental analysis research. They also outperform the factor-based and parametric portfolio policy approaches used in the prior portfolio optimization literature. The relative performance gains from mean-variance optimized fundamental portfolios are persistent through time, robust to eliminating small capitalization firms from the investment set, and robust to incorporating estimated transactions costs. Our results suggest that future fundamental analysis research could implement this portfolio optimization approach to provide greater investment insights. © 2022 American Accounting Association. All rights reserved. | P4: fundamental analysis; fundamentals-based expected returns; modeling; portfolio optimization; valuation | R4: Article | S4: Final | U4: Scopus | V4: 2-s2.0-85132667755
A5: Gallemore J.; Jacob M. | B5: Gallemore, John (56194898700); Jacob, Martin (37028466200) | C5: 56194898700; 37028466200 | D5: Corporate Tax Enforcement and Business Activity | E5: 2025 | F5: Accounting Review | G5: 100 | H5: 1 | J5: 231 | K5: 260 | L5: 9 | M5: 10.2308/TAR-2023-0011 | N5: https://www.scopus.com/inward/record.uri?eid=2-s2.0-85215000470&doi=10.2308%2FTAR-2023-0011&partnerID=40&md5=6eb2bd63531c6a09ba03fa469584d277 | O5: We examine the consequences of corporate tax enforcement for business activity. Using two different empirical approaches—a regional design and a firm-level design—we document that corporate tax enforcement is negatively associated with business activity, as measured by establishments and employment. This association is economically significant and is robust to tests that mitigate concerns regarding endogeneity and measurement. Furthermore, we find that the negative association between tax enforcement and business activity varies substantially in the cross-section. Specifically, we find that it is weaker for regions and firms with greater access to external financing sources and is stronger for regions and firms where compliance costs are likely higher and for which the ex ante costs of tax enforcement are greater. Our findings suggest that the effects of tax enforcement on business activity are economically important and heterogeneous, which should be of interest to academics and policymakers. © 2025 American Accounting Association. All rights reserved. | P5: business activity; compliance costs; corporate tax enforcement; employment; local economies | R5: Article | S5: Final | T5: All Open Access; Bronze Open Access | U5: Scopus | V5: 2-s2.0-85215000470
A6: Glaeser S.; Schonberger B.; Wasley C.E.; Xiao J.J. | B6: Glaeser, Stephen (57195741898); Schonberger, Bryce (57213197271); Wasley, Charles E. (6507362682); Xiao, Jason J. (57225928882) | C6: 57195741898; 57213197271; 6507362682; 57225928882 | D6: Private Information Acquisition via Freedom of Information Act Requests Made to the Securities and Exchange Commission | E6: 2023 | F6: Accounting Review | G6: 98 | H6: 3 | J6: 229 | K6: 255 | L6: 7 | M6: 10.2308/TAR-2021-0146 | N6: https://www.scopus.com/inward/record.uri?eid=2-s2.0-85162804594&doi=10.2308%2FTAR-2021-0146&partnerID=40&md5=df8e900bae32f7ec7062a0a525f40dde | O6: There is limited evidence about when, why, and which individuals incur costs to acquire nonpublic information about a firm, largely due to the difficulty of observing private information acquisition. To overcome this difficulty, we obtain data on Freedom of Information Act (FOIA) requests submitted to the Securities and Exchange Commission (SEC). We predict and find that perceived information asymmetry between managers and outsiders resulting from both proprietary and agency costs triggers FOIA search. We categorize organizations making FOIA requests using their business descriptions and find that many, including law and intellectual property firms, are not expressly interested in obtaining information for near-term equity trading. Instead, their search activity relates to determinants beyond financial characteristics, including patent litigation and executive turnover. Taken together, we provide evidence on private information search by a relatively unexamined set of organizations and shed new light on the function of the SEC’s Office of FOIA Services. © 2023 American Accounting Association. All rights reserved. | P6: agency costs; competition; disclosure; Freedom of Information Act; information acquisition; information search; lawsuits; proprietary costs | R6: Article | S6: Final | U6: Scopus | V6: 2-s2.0-85162804594
A7: Tegeler A.C.; Brown V.L.; Downey D.H. | B7: Tegeler, Amy C. (57201384840); Brown, Veena L. (56599909300); Downey, Denise Hanes (57202337345) | C7: 57201384840; 56599909300; 57202337345 | D7: Auditor Perceptions, Reactions, and Responses to PCAOB Inspection Feedback | E7: 2025 | F7: Accounting Review | G7: 100 | H7: 1 | J7: 437 | K7: 464 | L7: 1 | M7: 10.2308/TAR-2023-0021 | N7: https://www.scopus.com/inward/record.uri?eid=2-s2.0-85214571410&doi=10.2308%2FTAR-2023-0021&partnerID=40&md5=84933b1a7cfe8803bf9d6f20701ef102 | O7: Guided by the performance feedback literature, we study PCAOB inspections as a nonstandard feedback event. We use an experiential questionnaire to collect and analyze perceptions, reactions, and responses to inspection feedback from 120 partners and managers subject to a recent PCAOB inspection. Despite varying perceptions, we find on average auditors perceive strong firm support but also that firms acquiesce to inspectors. Generally, the feedback source, inspectors, are perceived as professional, organized, and knowledgeable and auditors agree with the feedback message, perceiving it as consistent and well reasoned. We observe a range of auditor reactions (satisfaction with and motivated to use inspection feedback), responses at the engagement level (improvements to audit quality and inspection risk or impression management), and individual responses. Multivariate analyses show more positive feedback perceptions improve reactions, which enhance desirability of responses and are robust to considering the inspection outcome, offering insights for refining inspection interactions and processes. © 2025 American Accounting Association. All rights reserved. | P7: audit inspections; audit quality; experiential questionnaire; feedback; inspection impression management; PCAOB | R7: Article | S7: Final | U7: Scopus | V7: 2-s2.0-85214571410
A8: Gunn J.L.; Li C.; Liao L.; Zhou S. | B8: Gunn, Joshua L. (57198420906); Li, Chan (24071088600); Liao, Lin (56045006800); Zhou, Shan (55648845500) | C8: 57198420906; 24071088600; 56045006800; 55648845500 | D8: Is It Better to Kill Two Birds with One Stone? Internal Control Audit Quality and Audit Costs for Integrated versus Nonintegrated Audits | E8: 2023 | F8: Accounting Review | G8: 98 | H8: 1 | J8: 251 | K8: 283 | L8: 23 | M8: 10.2308/TAR-2019-0220 | N8: https://www.scopus.com/inward/record.uri?eid=2-s2.0-85161800226&doi=10.2308%2FTAR-2019-0220&partnerID=40&md5=599c342351a22ec08e3f8194bdc8690f | O8: Audits of internal control over financial reporting (ICFR) are typically “integrated” with the audit of the financial statements (FSs)—both audits are conducted by the same audit firm, which designs procedures to satisfy the objectives of both audits simultaneously. A common assumption is that integrating the two audits is more effective and efficient than performing them separately. However, this assumption has not been tested empirically. Using a sample of Chinese companies that employ different audit firms for their FS and ICFR audits (i.e., nonintegrated auditors), we find evidence that challenges this assumption. Specifically, we find ICFR audit quality is higher for nonintegrated audits compared to integrated audits. Moreover, total audit fees are lower for nonintegrated audits, despite higher ICFR audit fees. © 2023 American Accounting Association. All rights reserved. | P8: audit cost; audit quality; integrated audit; internal control over financial reporting; SOX | R8: Article | S8: Final | U8: Scopus | V8: 2-s2.0-85161800226
A9: Hayes R.M.; Tian X.; Wang X. | B9: Hayes, Rachel M. (7402082490); Tian, Xiaoli (58345641900); Wang, Xue (56477533700) | C9: 7402082490; 58345641900; 56477533700 | D9: Deregulation and Board Policies: Evidence from Performance and Risk Exposure Measures Used in Bank CEO Turnover Decisions | E9: 2023 | F9: Accounting Review | G9: 98 | H9: 3 | J9: 257 | K9: 283 | L9: 4 | M9: 10.2308/TAR-2018-0752 | N9: https://www.scopus.com/inward/record.uri?eid=2-s2.0-85162751978&doi=10.2308%2FTAR-2018-0752&partnerID=40&md5=65fcbde1b8f3041cc76e1b3e2f07f4d5 | O9: We examine the effects of banking deregulation on bank board policies—specifically, whether deregulation affects the performance and risk exposure measures used in bank CEO turnover decisions. Using the staggered adoption of interstate branching as our setting, we find that bank CEO turnover is more (less) sensitive to stock (accounting) performance after deregulation. We also find that deregulation is associated with a higher sensitivity of bank CEO turnover to the idiosyncratic component of tail risk. Moreover, such changes in turnover policies primarily exist in large banks and federally chartered banks, which are best positioned to exploit growth opportunities, and in banks that expand branch operations after deregulation. Our results indicate an increased emphasis on stock performance and tail risk in turnover decisions when growth opportunities are greater in the deregulated environment. The findings provide evidence that the information used in board decisions varies with features of the competitive environment. © 2023 American Accounting Association. All rights reserved. | P9: CEO turnover; deregulation; growth | R9: Article | S9: Final | U9: Scopus | V9: 2-s2.0-85162751978
A10: Griffin P.A.; Hong H.A.; Ryou J.W. | B10: Griffin, Paul A. (36015132500); Hong, Hyun A. (55894289400); Ryou, Ji Woo (57202872742) | C10: 36015132500; 55894289400; 57202872742 | D10: Proprietary Costs: Why Do R&D-Active Firms Choose Single-Lender Financing? | E10: 2022 | F10: Accounting Review | G10: 97 | H10: 6 | J10: 263 | K10: 296 | L10: 15 | M10: 10.2308/TAR-2018-0158 | N10: https://www.scopus.com/inward/record.uri?eid=2-s2.0-85138736055&doi=10.2308%2FTAR-2018-0158&partnerID=40&md5=c1a8b8a3c4506acb76d740eb6a92e4d9 | O10: We examine whether proprietary costs drive R&D-active firms’ choice of private loan structure. We find that R&D-active firms are more likely to choose single-lender over multi-lender private loan financing. This is consistent with the theory that high-ability entrepreneurs protect their proprietary knowledge by communicating it to a single lender while disclosing generic and less sensitive information to the public. This propensity, however, significantly decreases after the enactment of the American Inventor’s Protection Act (AIPA), which accelerated public disclosure of firms’ patent details in filings with the U.S. Patent and Trademark Office. This accelerated public disclosure potentially caused R&D information to spill over to rivals, increasing the proprietary costs of single-lender borrowers. AIPA enactment also increased the spread on R&D-active firms’ single-lender loans. These findings contribute to the voluntary disclosure and financing choice literature by linking R&D-active firms’ choice of single-lender financing to the proprietary costs of public disclosure. © 2022 American Accounting Association. All rights reserved. | P10: American Inventor’s Protection Act; financing innovation; proprietary costs; R&D-active firms; single-lender financing | R10: Article | S10: Final | U10: Scopus | V10: 2-s2.0-85138736055
A11: Loudis J.A. | B11: Loudis, Johnathan A. (16643179100) | C11: 16643179100 | D11: Stock Price Reactions to the Information and Bias in Analyst-Expected Returns | E11: 2024 | F11: Accounting Review | G11: 99 | H11: 4 | J11: 281 | K11: 313 | L11: 0 | M11: 10.2308/TAR-2022-0309 | N11: https://www.scopus.com/inward/record.uri?eid=2-s2.0-85197728221&doi=10.2308%2FTAR-2022-0309&partnerID=40&md5=b07d472c1c3ca1a97ed8724883e53ff5 | O11: I use a novel decomposition to estimate information and bias components from the returns implied by analyst price targets and provide evidence that prices simultaneously under-react to information and over-react to bias. Price reactions to information are permanent, and prices drift in the direction of their initial reaction for up to 12 months. Price reactions to bias are transitory, and prices reverse their initial reaction after about three months. Price reactions are relatively efficient. Approximately 85 percent of the total price reaction to information occurs during price target announcement months. Market participants are able to mostly (but not fully) debias analyst-expected returns before incorporating them into prices, with the announcement-month reaction to bias being relatively weak at about 15 percent of its reaction to information. A trading strategy analysis implies that mispricing induced by bias is only about one-third of that implied by prior research. © 2024 American Accounting Association. All rights reserved. | P11: analysts; cross-section; expected returns; market efficiency; price drift; price targets; return reversal | R11: Article | S11: Final | T11: All Open Access; Bronze Open Access | U11: Scopus | V11: 2-s2.0-85197728221
A12: Bentley J.W.; Lambert T.A.; Wang E. | B12: Bentley, Jeremiah W. (57189918952); Lambert, Tamara A. (53664036100); Wang, Elaine (55558004700) | C12: 57189918952; 53664036100; 55558004700 | D12: The Effect of Increased Audit Disclosure on Managers’ Real Operating Decisions: Evidence from Disclosing Critical Audit Matters | E12: 2021 | F12: Accounting Review | G12: 96 | H12: 1 | J12: 23 | K12: 40 | L12: 62 | M12: 10.2308/TAR-2017-0486 | N12: https://www.scopus.com/inward/record.uri?eid=2-s2.0-85101257543&doi=10.2308%2FTAR-2017-0486&partnerID=40&md5=c83885c8436a1f61fd2a29c123868233 | O12: We investigate whether and how a ‘‘critical audit matter’’ (CAM) disclosure affects managers’ real operating decisions in two contexts (issuing a loan that decreases versus increases the average risk profile of loan portfolios, or choosing to hedge versus speculate on commodity risk). We expect that a CAM disclosure increases disclosure costs and implies expanded auditor support for both types of activities, but we expect implied auditor support to be valued more highly for risk-increasing than for risk-decreasing activities. As a result, we predict that a CAM disclosure decreases managers’ risk-decreasing activities (due to increased disclosure costs) more than managers’ risk-increasing activities (as the implied auditor support counteracts the increased disclosure costs). We find evidence consistent with our prediction across multiple experiments. Our study sheds light on the unintended consequences of a CAM disclosure and provides insight to relevant parties as the new standard goes into effect. © 2021 American Accounting Association. All rights reserved. | P12: Auditor reporting model; Critical audit matters (CAMs); Disclosure efficiency; Managers’ real operating decisions; Operating distortion | R12: Article | S12: Final | U12: Scopus | V12: 2-s2.0-85101257543
A13: Ashraf M.; Sunder J. | B13: Ashraf, Musaib (57219866977); Sunder, Jayanthi (16240040800) | C13: 57219866977; 16240040800 | D13: Can Shareholders Benefit from Consumer Protection Disclosure Mandates? Evidence from Data Breach Disclosure Laws | E13: 2023 | F13: Accounting Review | G13: 98 | H13: 4 | J13: 1 | K13: 32 | L13: 34 | M13: 10.2308/TAR-2020-0787 | N13: https://www.scopus.com/inward/record.uri?eid=2-s2.0-85146311296&doi=10.2308%2FTAR-2020-0787&partnerID=40&md5=745a055e0cc6244dab8d6ed7afbcef01 | O13: Data breach disclosure laws are state-level disclosure mandates intended to protect individuals from the consequences of identity theft. However, we argue that the laws help reduce shareholder risk by encouraging managers to take real actions to reduce firms' exposure to cyber risk. Consistent with this argument, we find an onaverage decrease in shareholder risk, proxied by cost of equity, after the staggered passage of these laws. We also find the effect is attenuated for firms that already took real actions to manage cyber risk before the laws. Further, after these laws, firms are more likely to increase cybersecurity investments and have a cybersecurity officer. Finally, we observe positive abnormal returns on key dates related to the passage of these laws. Our collective evidence suggests that consumer protection disclosure mandates can benefit shareholders and, specifically, that regulators can use disclosure mandates to incentivize managers to reduce firms' exposure to cyber risk. © 2023 American Accounting Association. All rights reserved. | P13: capital markets; consumer protection; corporate governance; cost of capital; cyber risk; cybersecurity; disclosure; disclosure mandates; information technology; real effects | R13: Article | S13: Final | U13: Scopus | V13: 2-s2.0-85146311296
A14: Burke J.J.; Hoitash R.; Hoitash U.; Xiao S. | B14: Burke, Jenna J. (57141536900); Hoitash, Rani (20433597800); Hoitash, Udi (24337937400); Xiao, Summer (57222093671) | C14: 57141536900; 20433597800; 24337937400; 57222093671 | D14: The Disclosure and Consequences of U.S. Critical Audit Matters | E14: 2023 | F14: Accounting Review | G14: 98 | H14: 2 | J14: 59 | K14: 95 | L14: 104 | M14: 10.2308/TAR-2021-0013 | N14: https://www.scopus.com/inward/record.uri?eid=2-s2.0-85175458078&doi=10.2308%2FTAR-2021-0013&partnerID=40&md5=2997d71c36797ab53bd5f402e72607ef | O14: This study uses difference-in-differences (DiD) analyses to examine the consequences of adopting the U.S. critical audit matter (CAM) disclosure requirement for preparers and users of financial reports. The CAM requirement is one of the largest expansions of the U.S. audit report since the 1940s. We document significant changes to financial statement footnotes referenced by CAMs, which suggests an indirect consequence where management disclosure changes in areas that are expected to be scrutinized following auditor-provided disclosure. Results also suggest that, on average, CAM disclosures do not provide incremental information to the market. To further examine market reaction, we develop well-specified prediction models for the expected number and subject areas of CAMs. We find limited initial evidence that the market reacts negatively when unexpected CAMs are disclosed. Overall, our findings provide insights on the new CAM standard and particularly demonstrate its relevance to management disclosure decisions and to the market. © 2023 American Accounting Association. All rights reserved. | P14: audit fees; audit quality; critical audit matters; expanded audit report; footnote disclosure; market reaction; PCAOB; textual analysis; unexpected disclosures; XBRL | R14: Article | S14: Final | U14: Scopus | V14: 2-s2.0-85175458078
A15: Chen Y.; Ofosu E.; Pittman J. | B15: Chen, Yangyang (55224388500); Ofosu, Emmanuel (57455133200); Pittman, Jeffrey (7102551904) | C15: 55224388500; 57455133200; 7102551904 | D15: The Cost of Investor Protection: Bank Loan Contracting During SEC Investigations | E15: 2026 | F15: Accounting Review | G15: 101 | H15: 1 | J15: 203 | K15: 234 | L15: 1 | M15: 10.2308/TAR-2024-0405 | N15: https://www.scopus.com/inward/record.uri?eid=2-s2.0-105030514518&doi=10.2308%2FTAR-2024-0405&partnerID=40&md5=221a2e9d7110d36a2a48cf8da216226a | O15: In examining the loan contracting implications of SEC investigations, we document that banks charge higher loan spreads when borrowers are under investigation, with the rise in interest rates varying predictably with lender characteristics. Further, our evidence implies that the debt pricing impact of SEC investigations is amplified for borrowers suffering worse credit quality and information asymmetry as well as those relying more on bank loans. These findings suggest that banks perceive increased risk for borrowers under SEC scrutiny while also leveraging their knowledge of the investigations to extract rents. Supplemental analyses reveal tighter nonspread loan terms and a higher likelihood of amending existing loan contracts during SEC investigations. Additionally, the tightening of loan terms reverses for investigations that conclude without enforcement actions. Overall, our research identifies an economic cost of SEC investigations and alerts regulators to these costs when deciding whether to launch an investigation. © 2026, American Accounting Association. All rights reserved. | P15: bank loan contracting; lending risk; private information; rent extraction; SEC investigation | R15: Article | S15: Final | T15: All Open Access; Bronze Open Access | U15: Scopus | V15: 2-s2.0-105030514518
A16: Kim S.; Kim S.; Ryan S.G. | B16: Kim, Sehwa (57226112834); Kim, Seil (57213778876); Ryan, Stephen G. (35574572600) | C16: 57226112834; 57213778876; 35574572600 | D16: Banks’ Motivations for Designating Securities as Held to Maturity | E16: 2025 | F16: Accounting Review | G16: 100 | H16: 4 | J16: 303 | K16: 330 | L16: 1 | M16: 10.2308/TAR-2023-0615 | N16: https://www.scopus.com/inward/record.uri?eid=2-s2.0-105009652064&doi=10.2308%2FTAR-2023-0615&partnerID=40&md5=253d2a3043c41bd2edbb5cce029157cd | O16: We provide evidence that banks classify fixed-rate debt investment securities as held to maturity (HTM) rather than as available for sale (AFS) when HTM classification provides preferred financial accounting and regulatory capital treatments, not because they have a distinct economically motivated intent and ability to hold the securities to maturity. Specifically, we document predictably divergent security classifications by three categories of banks that differ in whether the regulatory accumulated other comprehensive income (AOCI) filter, which removes AOCI from Tier 1 capital, applies in four subperiods of our 2012–2022 sample period. The boundaries of the subperiods reflect changes in the AOCI filter’s applicability in 2014 and 2019 and the sharp rise in interest rates beginning in late 2021. We further find that the bank categories differ in the interest rate risk of their AFS securities and the extents to which they economically hedge that risk using derivatives and uninsured deposits. © 2025 American Accounting Association. All rights reserved. | P16: AOCI filter; banks; held to maturity; investment securities; regulatory capital | R16: Article | S16: Final | T16: All Open Access; Bronze Open Access | U16: Scopus | V16: 2-s2.0-105009652064
A17: Chen J.; Dou Y.; Zou Y. | B17: Chen, Jing (57016173800); Dou, Yiwei (56273698300); Zou, Youli (56706771300) | C17: 57016173800; 56273698300; 56706771300 | D17: Information externalities of sfas 161: Evidence from supply chains | E17: 2021 | F17: Accounting Review | G17: 96 | H17: 4 | J17: 179 | K17: 202 | L17: 17 | M17: 10.2308/TAR-2018-0578 | N17: https://www.scopus.com/inward/record.uri?eid=2-s2.0-85111536189&doi=10.2308%2FTAR-2018-0578&partnerID=40&md5=741a94afc9cfa7861d6d48c9101d56cc | O17: Effective in 2009, SFAS 161 requires enhanced disclosures about derivative use and hedging activities. We test for changes to the information environment of firms whose disclosure policy is unaffected by this standard directly. Using a sample of non-users of derivatives, we find an increase in stock liquidity after their critical customers expand derivative disclosures under SFAS 161. The effect persists for one year and becomes insignificant in subsequent years as the firms dial back their voluntary disclosure. The effect is also more salient for firms that have stronger economic links with their customers and for firms whose customers exhibit more significant improvements in derivative disclosures. The findings suggest that the mandatory derivative disclosures due to SFAS 161 lead to short-term positive information externalities along supply chains. © 2021 American Accounting Association. All rights reserved. | P17: Disclosure regulation; Hedge accounting; Information externalities; Market liquidity; SFAS 161; Supply chains | R17: Article | S17: Final | U17: Scopus | V17: 2-s2.0-85111536189
A18: Hawkins S.R.; Pickerd J.; Summers S.L.; Wood D.A. | B18: Hawkins, Steven R. (57209739649); Pickerd, Jeffrey (49663865200); Summers, Scott L. (7007176901); Wood, David A. (7404401863) | C18: 57209739649; 49663865200; 7007176901; 7404401863 | D18: The Development of the Process Mining Event Log Generator (PMELG) Tool | E18: 2023 | F18: Accounting Review | G18: 35 | H18: 3 | L18: 1 | M18: 10.2308/HORIZONS-2022-153 | N18: https://www.scopus.com/inward/record.uri?eid=2-s2.0-85173742967&doi=10.2308%2FHORIZONS-2022-153&partnerID=40&md5=77c043d60aaa89e48e943fe12c4f84a8 | O18: Process mining is an emerging technology that allows users to visualize all potential variations of business processes within an organization. It holds significant potential for impacting the field of accounting. However, training professionals and students in its use is challenging due to a lack of event data applicable to accounting and auditing scenarios. To address this issue, we developed an easy-to-use tool called the Process Mining Event Log Generator (PMELG) for generating process mining data files for the order-to-cash process. With the PMELG tool, users can create realistic datasets that incorporate key accounting and auditing concepts, such as segregation of duties issues, internal control violations, operational inefficiencies, and fraudulent behavior. We validate this tool with professionals and academics. Both groups believe the tool will be beneficial for both practitioners and academic audiences. © 2023 American Accounting Association. All rights reserved. | P18: data analytics; data generation; event logs; process mining | R18: Article | S18: Final | U18: Scopus | V18: 2-s2.0-85173742967
A19: Feng F.Z.; Wang W.; Wu Y.; Zhang G. | B19: Feng, Felix Zhiyu (57196058422); Wang, Wenyu (57201008264); Wu, Yufeng (59511581200); Zhang, Gaoqing (57190688749) | C19: 57196058422; 57201008264; 59511581200; 57190688749 | D19: Ignorance Is Bliss: The Screening Effect of (Noisy) Information | E19: 2025 | F19: Accounting Review | G19: 100 | H19: 1 | J19: 201 | K19: 230 | L19: 2 | M19: 10.2308/TAR-2023-0112 | N19: https://www.scopus.com/inward/record.uri?eid=2-s2.0-85214802925&doi=10.2308%2FTAR-2023-0112&partnerID=40&md5=2a927e3506f372de37108686701e1250 | O19: This paper studies the value of a firm’s internal information when the firm faces an adverse selection problem arising from unobservable managerial abilities. Although more precise information allows the firm to make ex post more efficient investment decisions, noisier information has an ex ante screening effect that allows the firm to attract on-average better managers. The tradeoff between more effective screening of managers and more informed investment implies a nonmonotonic relationship between firm value and information quality. A marginal improvement in information quality does not necessarily lead to an overall improvement in firm value. © 2025 American Accounting Association. All rights reserved. | P19: accounting noise; corporate governance; internal information; screening | R19: Article | S19: Final | U19: Scopus | V19: 2-s2.0-85214802925
A20: Kachelmeier S.J.; Webb R.A.; Williamson M.G. | B20: Kachelmeier, Steven J. (6506220075); Webb, R. Alan (57687898300); Williamson, Michael G. (23098716300) | C20: 6506220075; 57687898300; 23098716300 | D20: Do Performance-Contingent Incentives Help or Hinder Divergent Thinking? | E20: 2024 | F20: Accounting Review | G20: 99 | H20: 2 | J20: 229 | K20: 248 | L20: 1 | M20: 10.2308/TAR-2020-0751 | N20: https://www.scopus.com/inward/record.uri?eid=2-s2.0-85187711993&doi=10.2308%2FTAR-2020-0751&partnerID=40&md5=4bdf64bbcb3e7de246494f3a422f4b66 | O20: Toward the goal of reconciling conflicting arguments on whether performance-based incentives facilitate or impede divergent thinking, we identify a feature common to prior demonstrations of negative incentive effects: they generally involve tasks with only one correct solution. Our first experiment replicates a negative incentive effect when insight problems require “bottom-up” divergent thinking from an unexpected resource to the problem it is uniquely equipped to solve, whereas our second experiment finds a positive incentive effect in the more general case of problems that enable “top-down” divergent thinking from a problem to multiple potential solutions. We also observe a positive incentive effect in a third experiment that measures the time needed to generate a solution to problems that have multiple potential solutions and in a fourth experiment in which participants design insight problems. Overall, our findings suggest that any harmful effects of performance-based incentives are likely restricted to highly constrained settings. © 2024 American Accounting Association. All rights reserved. | P20: creativity; divergent thinking; incentives; insight problems; top-down versus bottom-up reasoning | R20: Article | S20: Final | U20: Scopus | V20: 2-s2.0-85187711993
A21: Beneish M.D.; Farber D.B.; Glendening M.; Shaw K.W. | B21: Beneish, Messod D. (6603303677); Farber, David B. (23491780200); Glendening, Matthew (57193741378); Shaw, Kenneth W. (7202206489) | C21: 6603303677; 23491780200; 57193741378; 7202206489 | D21: Aggregate Financial Misreporting and the Predictability of U.S. Recessions and GDP Growth | E21: 2023 | F21: Accounting Review | G21: 98 | H21: 5 | J21: 129 | K21: 159 | L21: 3 | M21: 10.2308/TAR-2021-0160 | N21: https://www.scopus.com/inward/record.uri?eid=2-s2.0-85162007700&doi=10.2308%2FTAR-2021-0160&partnerID=40&md5=860e9b6bb03e112ea769b8ea6434edda | O21: This study examines the incremental predictive power of aggregate measures of financial misreporting for recession and real gross domestic product (GDP) growth. We draw on prior research suggesting that misreporting has real economic effects because it represents misinformation on which firms base their investment, hiring, and production decisions. We find that aggregate M-Score incrementally predicts recessions at forecast horizons of five to eight quarters ahead. We also find that aggregate M-Score is significantly associated with lower future growth in real GDP, real investment, consumption, and industrial production. Additionally, our result that aggregate M-Score predicts lower real investment one to four quarters ahead partially accounts for why misreporting predicts recessions five to eight quarters ahead. Our findings are weaker when we use aggregate F-Score as a proxy for misreporting. Overall, this study provides novel evidence that aggregate misreporting measures can aid forecasters and regulators in predicting recessions and real GDP growth. © 2023 American Accounting Association. All rights reserved. | P21: financial misreporting; GDP; prediction; recessions | R21: Article | S21: Final | U21: Scopus | V21: 2-s2.0-85162007700
A22: Dodgson M.K.; Agoglia C.P.; Bennett G.B. | B22: Dodgson, Mary Kate (57216788494); Agoglia, Christopher P. (6506359364); Bennett, G. Bradley (56542534400) | C22: 57216788494; 6506359364; 56542534400 | D22: The Effect of Negative Expectancy Violations and Relational Familiarity on Client Managers’ Negotiation Positions | E22: 2023 | F22: Accounting Review | G22: 35 | H22: 3 | J22: 1 | K22: 24 | L22: 2 | M22: 10.2308/TAR-2017-0528 | N22: https://www.scopus.com/inward/record.uri?eid=2-s2.0-85173773203&doi=10.2308%2FTAR-2017-0528&partnerID=40&md5=39be31753550b4e122d7fa612fd199f5 | O22: During the interactive process of issue resolution, client managers may develop expectations about the auditor’s position. We examine the effect that negative expectancy violations have on managers’ pre-negotiation positions and how relational familiarity can moderate this effect. Through a series of experiments, we find that, when the partner’s proposed adjustment is within the client’s original expectations, managers offer greater concessions to a more familiar partner than to a less familiar partner. However, depending on relational familiarity, client managers react to expectancy violations very differently. Managers react more severely when a more familiar partner violates expectations, offering lower negotiation concessions than when no violation occurs. In contrast, managers tend to ignore violations committed by a less familiar partner, offering similar negotiation concessions whether or not a violation has occurred. Furthermore, we find support for a practical intervention to repair damage from expectancy violations committed by more familiar partners. © 2023 American Accounting Association. All rights reserved. | P22: auditor-client negotiation; auditor-client relationships; expectancy violations; partner tenure; relational familiarity; resolving audit differences | R22: Review | S22: Final | U22: Scopus | V22: 2-s2.0-85173773203
A23: Çetin F.M. | B23: Çetin, Furkan M. (60400357900) | C23: 60400357900 | D23: The Real Effects of Accounting on R&D Alliance Formations and Innovation: Evidence from ASC 606 | E23: 2026 | F23: Accounting Review | G23: 101 | H23: 1 | J23: 103 | K23: 135 | L23: 0 | M23: 10.2308/TAR-2022-0302 | N23: https://www.scopus.com/inward/record.uri?eid=2-s2.0-105030239500&doi=10.2308%2FTAR-2022-0302&partnerID=40&md5=d4dec97e0c7161100a4f69485bfd8797 | O23: I examine how Accounting Standards Codification (ASC) 606 affects R&D alliance formations and innovation in the drug development industry. ASC 606 alters revenue recognition timing and increases disclosure requirements. I document that firms dependent on R&D alliance revenues accelerate revenue recognition and expand revenue-related disclosures following ASC 606 adoption. These concurrent changes reduce information asymmetry, both between firms and between managers and investors, but only when increased disclosure accompanies accelerated recognition. Consistent with these net reductions in information asymmetry, affected firms raise more equity capital and increase R&D investment. Notably, these firms, which historically acted as technology providers (principals), form more R&D alliances as technology acquirers (partners). Consequently, they exhibit higher innovation output, measured by new patents and drug candidates. This study identifies a specific mechanism through which accounting standards can stimulate innovation: reduced information asymmetry that facilitates strategic R&D alliance formation. © 2026, American Accounting Association. All rights reserved. | P23: ASC 606; innovation; R&D alliances; real effects; revenue recognition | R23: Article | S23: Final | T23: All Open Access; Bronze Open Access; Green Open Access | U23: Scopus | V23: 2-s2.0-105030239500
A24: Smith K.C. | B24: Smith, Kevin C. (57194875446) | C24: 57194875446 | D24: An Option-Based Approach to Measuring Disclosure Asymmetry | E24: 2023 | F24: Accounting Review | G24: 98 | H24: 4 | J24: 373 | K24: 403 | L24: 2 | M24: 10.2308/TAR-2020-0623 | N24: https://www.scopus.com/inward/record.uri?eid=2-s2.0-85168457899&doi=10.2308%2FTAR-2020-0623&partnerID=40&md5=ffd752762f8bd222100be6e1e43ee707 | O24: In this paper, I develop a measure of the difference in the amount of information that investors expect a forthcoming disclosure to contain should it reveal good news versus bad news (the disclosure's "asymmetry"). To do so, I first show that this asymmetry is linked to the skewness of returns that the disclosure creates. I then show that this skewness can be measured using a weighted change in option-implied return skewness leading up to the disclosure's release. The measure's ability to capture investors' prior beliefs regarding asymmetry is advantageous when studying ex ante decisions including contracting and information acquisition choices. I implement it on a sample of large firms' quarterly earnings announcements, finding evidence that investors anticipate cross-sectional but not time-series variation in earnings' asymmetry. © 2023 American Accounting Association. All rights reserved. | P24: conservatism; disclosure; earnings announcements; implied volatility; model-free implied skewness; option prices; skewness; volatility surface | R24: Article | S24: Final | U24: Scopus | V24: 2-s2.0-85168457899
A25: García-Feijóo L.; Jensen T.K.; Koch P.D. | B25: García-Feijóo, Luis (9747559700); Jensen, Tyler K. (57201338065); Koch, Paul D. (7202929123) | C25: 9747559700; 57201338065; 7202929123 | D25: Operating Leverage and Stock Returns under Different Aggregate Funding Conditions | E25: 2024 | F25: Accounting Review | G25: 99 | H25: 3 | J25: 169 | K25: 199 | L25: 2 | M25: 10.2308/TAR-2022-0051 | N25: https://www.scopus.com/inward/record.uri?eid=2-s2.0-85192317995&doi=10.2308%2FTAR-2022-0051&partnerID=40&md5=07e0fd145e14c50c0a124919ef0fa019 | O25: We document time-varying interrelations between aggregate funding conditions and the impact of operating leverage (OL) on stock returns. OL represents a primitive source of risk, which helps explain the well established unconditional relation between OL and future returns. However, the outperformance of firms with high OL occurs exclusively during periods of unconstrained funding. Although high OL represents operational inflexibility, when the Fed eases funding constraints, improved capital availability mitigates this inflexibility. Consequently, investors bid up the prices of stocks with high OL when aggregate funding constraints are loosened to reflect their lower risk and greater expected performance in unconstrained periods. © 2024 American Accounting Association. All rights reserved. | P25: aggregate funding conditions; monetary policy; operating leverage; sticky input prices; time-varying risk premium | R25: Article | S25: Final | U25: Scopus | V25: 2-s2.0-85192317995
A26: Rimkus D. | B26: Rimkus, Dan (57218670104) | C26: 57218670104 | D26: Client Social Status and Cooperation with Audit Requests | E26: 2024 | F26: Accounting Review | G26: 99 | H26: 3 | J26: 429 | K26: 449 | L26: 5 | M26: 10.2308/TAR-2022-0307 | N26: https://www.scopus.com/inward/record.uri?eid=2-s2.0-85192317879&doi=10.2308%2FTAR-2022-0307&partnerID=40&md5=acb91e3145daffee40b7fa84058312b4 | O26: Auditors collect evidence from clients that vary in social status. I investigate how these status differences interact with the costliness of auditor requests, thereby influencing client cooperation during evidence collection. I develop theory predicting that higher-status clients’ cooperation decisions will be more sensitive to differences in the costliness of requests than lower-status clients’ decisions. I test this theory across two experiments using multiple methods, leveraging the complementary strengths of each method. Experiment 1 is a more abstract experiment in the tradition of experimental economics, and Experiment 2 is a more contextualized experiment using participants with prior experience interacting with auditors. Results from both experiments support the theorized interaction between the costliness of audit requests and client social status. This conclusion carries implications for practitioners in assessing strategic tactics that will efficiently and effectively increase client cooperation. © 2024 American Accounting Association. All rights reserved. | P26: audit evidence; auditor-client interaction; client cooperation; status | R26: Article | S26: Final | U26: Scopus | V26: 2-s2.0-85192317879
A27: Edwards A.; Kubata A.; Shevlin T. | B27: Edwards, Alexander (55419774200); Kubata, Adrian (56192431800); Shevlin, Terry (6601990549) | C27: 55419774200; 56192431800; 6601990549 | D27: The decreasing trend in U.S. cash effective tax rates: The role of growth in pre-tax income | E27: 2021 | F27: Accounting Review | G27: 96 | H27: 5 | J27: 231 | K27: 261 | L27: 28 | M27: 10.2308/TAR-2019-0252 | N27: https://www.scopus.com/inward/record.uri?eid=2-s2.0-85107132059&doi=10.2308%2FTAR-2019-0252&partnerID=40&md5=83c99e91a277908f96691a80c42037d9 | O27: We develop a linear corporate tax function where taxes paid are regressed on pre-tax income and an intercept. We show that if the intercept is positive, cash ETRs are a convex function of pre-tax income. We present large-sample evidence consistent with this ETR convexity. Thus, although firms may have stable linear tax functions (i.e., constant parameters in the linear tax model) representing stable tax avoidance behavior, ETRs can change over time because of growth in pre-tax income. Consequently, simply examining changes (or differences) in cash ETRs is nondiagnostic about whether tax avoidance has changed over time (or differs across firms). We illustrate our argument by showing that all of the observed downward trend in cash ETRs documented by Dyreng et al. (2017) can be explained by growth in pre-tax income. The wholesale concern about increased tax avoidance over time might be overstated. © 2021 American Accounting Association. All rights reserved. | P27: Cash effective tax rate; Corporate tax function; Time trend | R27: Article | S27: Final | U27: Scopus | V27: 2-s2.0-85107132059
A28: Ahn B.H.; Bushman R.M.; Patatoukas P.N. | B28: Ahn, Byung Hyun (59207132100); Bushman, Robert M. (6603387885); Patatoukas, Panos N. (53985113200) | C28: 59207132100; 6603387885; 53985113200 | D28: Under the Hood of Activist Fraud Campaigns: Private Information Quality, Disclosure Incentives, and Stock Lending Dynamics | E28: 2024 | F28: Accounting Review | G28: 99 | H28: 6 | J28: 1 | K28: 26 | L28: 4 | M28: 10.2308/TAR-2023-0392 | N28: https://www.scopus.com/inward/record.uri?eid=2-s2.0-85208678081&doi=10.2308%2FTAR-2023-0392&partnerID=40&md5=4cd2ab76414c814629d59abb68bb8289 | O28: Although activist short sellers can play a crucial role in fraud detection, they have come under scrutiny following accusations of systematically disseminating false negative information. We develop a framework delineating the roles of campaign-specific private information quality and short-selling dynamics in shaping disclosure incentives. We predict that the act of disclosure combined with pre-disclosure stock lending dynamics is informative about the quality of an activist's private information. We find that increased pre-disclosure shorting intensity is associated with more negative post-disclosure returns, adverse media coverage, and consequential campaign outcomes, including auditor turnover, accounting restatements, class-action lawsuits, and performancerelated delistings. Furthermore, elevated short-selling costs and risks magnify the association between predisclosure shorting intensity and post-disclosure underperformance. Finally, we examine V-shaped reversals and short covering following activists' disclosures and find no evidence of systematic manipulation. We conclude that activists disclosing fraud allegations under their own names are discouraged from engaging in "short-and-distort" schemes. © 2024 American Accounting Association. All rights reserved. | P28: activist short sellers; disclosure; fraud detection; stock lending market | R28: Article | S28: Final | U28: Scopus | V28: 2-s2.0-85208678081
A29: Basu S.; Kaviani M.S.; Maleki H. | B29: Basu, Sudipta (7403656354); Kaviani, Mahsa S. (57218330457); Maleki, Hosein (57218326685) | C29: 7403656354; 57218330457; 57218326685 | D29: Bank Entry Barriers and Firms’ Risk-Taking | E29: 2025 | F29: Accounting Review | G29: 100 | H29: 1 | J29: 55 | K29: 85 | L29: 2 | M29: 10.2308/TAR-2021-0604 | N29: https://www.scopus.com/inward/record.uri?eid=2-s2.0-85214894736&doi=10.2308%2FTAR-2021-0604&partnerID=40&md5=d94a89a0bb683948dfda7475833bdda3 | O29: We study how nonfinancial firms’ operating risks change after bank competition increases. By exploiting the 1990s staggered regulatory reforms across U.S. states that allowed interstate banking and branching, we show that out-of-state bank entry was associated with lower borrower risk-taking on average. Large, profitable, safe, and geographically diversified firms signed up as new clients of large entrant banks, which offered larger and cheaper loans that reflected their higher efficiency and risk reduction through geographical diversification. We argue that these large banks could substitute for local relationship lending with more data collection from branches in multiple states. Firms that began borrowing from entrant banks increased capital expenditures and project-specific financing and kept R&D expenses stable but reduced R&D risk. Firms that continued borrowing from incumbent banks paid higher interest rates and increased their risk, suggesting that their credit access fell. States that opened up more had bigger changes in these outcomes. © 2025 American Accounting Association. All rights reserved. | P29: assortative matching; bank competition; barriers to entry; corporate risk-taking; operational risk | R29: Article | S29: Final | T29: All Open Access; Bronze Open Access | U29: Scopus | V29: 2-s2.0-85214894736
A30: Hecht G.; Maas V.S.; van Rinsum M. | B30: Hecht, Gary (7006773315); Maas, Victor S. (24537627400); van Rinsum, Marcel (55255149300) | C30: 7006773315; 24537627400; 55255149300 | D30: The Effects of Transparency and Group Incentives on Managers’ Strategic Promotion Behavior | E30: 2023 | F30: Accounting Review | G30: 98 | H30: 7 | J30: 239 | K30: 260 | L30: 7 | M30: 10.2308/TAR-2020-0208 | N30: https://www.scopus.com/inward/record.uri?eid=2-s2.0-85176396002&doi=10.2308%2FTAR-2020-0208&partnerID=40&md5=eee1a60c3ebc4c909193a45f47535685 | O30: We investigate managers’ propensity to engage in strategic promotion behavior. Strategic promotion behavior occurs when managers pursue personal economic interests when contributing to employee promotion decisions, such that the probability that relatively lower performing employees are selected for a promotion is increased. We develop theory about how two important organizational characteristics—transparency about individual performance levels and the presence of group incentives—jointly affect managers’ tendency to strategically influence promotion decisions. Using a stylized lab experiment, we find that transparency about individual performance levels decreases strategic promotion behavior when group incentives are absent but not when group incentives are present. We discuss how our findings contribute to our understanding of management accounting and control systems. © 2023 American Accounting Association. All rights reserved. | P30: discretion; experiment; fairness; incentives; performance evaluation; promotions; strategic behavior; teams; transparency | R30: Article | S30: Final | U30: Scopus | V30: 2-s2.0-85176396002
A31: Manthei K.; Sliwka D.; Vogelsang T. | B31: Manthei, Kathrin (55937566900); Sliwka, Dirk (6603137505); Vogelsang, Timo (57226102017) | C31: 55937566900; 6603137505; 57226102017 | D31: Information, Incentives, and Attention: A Field Experiment on the Interaction of Management Controls | E31: 2023 | F31: Accounting Review | G31: 98 | H31: 5 | J31: 455 | K31: 479 | L31: 13 | M31: 10.2308/TAR-2019-1065 | N31: https://www.scopus.com/inward/record.uri?eid=2-s2.0-85169790083&doi=10.2308%2FTAR-2019-1065&partnerID=40&md5=1bb478fe15e551f6fc3e0c07e2234c0a | O31: We study the profit effects and interplay of two core accounting practices in a field experiment in a large retail chain. In a 2 × 2 factorial design, we vary (1) whether store managers obtain decision-facilitating information on a profit metric and (2) whether they receive performance pay based on the same metric.We find that both practices increase profits significantly. In contrast to reasoning based on standard economic theory, we do not find complementarity between both interventions. Rather, we detect evidence in line with an attention-directing role of both practices: the introduction of each raises attention to the underlying objective, which induces a countervailing substitution effect. © 2023 American Accounting Association. All rights reserved. | P31: attention direction; complementarity; decision facilitating; decision influencing; field experiment; interdependency; management controls; performance pay | R31: Article | S31: Final | U31: Scopus | V31: 2-s2.0-85169790083
A32: Petrov E.; Stocken P.C. | B32: Petrov, Evgeny (57219669119); Stocken, Phillip C. (6603184010) | C32: 57219669119; 6603184010 | D32: Auditor Specialization and Information Spillovers | E32: 2022 | F32: Accounting Review | G32: 97 | H32: 7 | J32: 401 | K32: 428 | L32: 17 | M32: 10.2308/TAR-2020-0423 | N32: https://www.scopus.com/inward/record.uri?eid=2-s2.0-85130448465&doi=10.2308%2FTAR-2020-0423&partnerID=40&md5=e177796e7b26319bc22f5e932788e146 | O32: We study the determinants of auditor industry specialization, the impact of specialization on fees and audit quality, and a regulator's optimal choice of audit standards in the presence of specialization. In industries with correlated firm values, a specialist auditor enjoys synergies from information spillovers between clients. These spillovers, however, only induce a specialist to decrease audit effort when the cost of effort and the prior precision of the firms' values are low. We derive empirical predictions about the determinants of specialization, and show that specialization benefits firms through lower expected fees and higher audit reporting quality, but only enhances the usefulness of reports to investors when the specialist exerts high audit effort. In a regulated setting, a stricter audit standard affects fees through its impact on specialization. We provide conditions under which standards that maximize firm value will be more strict and less strict when a regulator recognizes synergies. © 2022 American Accounting Association. All rights reserved. | P32: audit fees; audit quality; auditor specialization; information spillovers; PCAOB regulation | R32: Article | S32: Final | U32: Scopus | V32: 2-s2.0-85130448465
A33: Hammersley J.S.; Ricci M.A. | B33: Hammersley, Jacqueline S. (13003935400); Ricci, Michael A. (57215932328) | C33: 13003935400; 57215932328 | D33: Using Audit Programs to Improve Auditor Evidence Collection | E33: 2021 | F33: Accounting Review | G33: 96 | H33: 1 | J33: 251 | K33: 272 | L33: 12 | M33: 10.2308/TAR-2018-0120 | N33: https://www.scopus.com/inward/record.uri?eid=2-s2.0-85101258851&doi=10.2308%2FTAR-2018-0120&partnerID=40&md5=e175d5a9e0cb90f7a7040ede4e0bffc8 | O33: Auditors experience difficulty auditing accounts for which it is difficult to identify in advance all the evidence necessary to perform an effective audit. These accounts are challenging because they commonly require auditors to collect additional, relevant evidence in response to new information received during evidence collection. We address this experimentally by examining whether changing the focus of audit programs from plan-focused (i.e., focused on the planned audit procedures) to goal-focused (i.e., focused on the task goal) improves auditors’ collection of relevant evidence that is not identifiable at audit program creation. We expect goal-focused auditors to remain open to more ways to achieve their goal. Consequently, we expect and find that goal-focused auditors collect more effective evidence than plan-focused auditors and follow up more effectively on this evidence. This suggests that a goal-focused approach improves audit quality on tasks requiring auditors to flexibly respond to new information. © 2021 American Accounting Association. All rights reserved. | P33: Audit planning; Audit programs; Evidence collection; Goals | R33: Article | S33: Final | U33: Scopus | V33: 2-s2.0-85101258851
A34: Hilary G.; Tian X.; Yu M. | B34: Hilary, Gilles (6505892271); Tian, Xiaoli (58345641900); Yu, Miaomiao (59940016300) | C34: 6505892271; 58345641900; 59940016300 | D34: Does Meeting Financial Expectations Boost Employee Satisfaction? | E34: 2025 | F34: Accounting Review | G34: 100 | H34: 4 | J34: 277 | K34: 302 | L34: 2 | M34: 10.2308/TAR-2022-0018 | N34: https://www.scopus.com/inward/record.uri?eid=2-s2.0-105009642006&doi=10.2308%2FTAR-2022-0018&partnerID=40&md5=3d3d3a4b12c801f8f43499296040b32d | O34: We investigate whether meeting Wall Street’s expectations affects rank-and-file employees’ satisfaction. Controlling for firms’ underlying financial performance, we find that those currently working for firms that meet or marginally beat analysts’ forecasts experience increased job satisfaction. This positive effect is concentrated among employees who are less transient, receive more nonexecutive stock options, or are more unionized. Furthermore, the positive effect exists only when employees do not incur higher costs associated with reaching the threshold because they overwork, suffer from labor law violations, or experience layoffs. Lastly, more senior or highly skilled employees respond more strongly when their employer meets Wall Street’s expectations. These results suggest that the effect of meeting earnings targets on employee satisfaction is significant when employees’ incentives align more with those of their employer or when employees are not unduly pressured. © 2025 American Accounting Association. All rights reserved. | P34: earnings targets; employee satisfaction; Glassdoor | R34: Article | S34: Final | T34: All Open Access; Bronze Open Access | U34: Scopus | V34: 2-s2.0-105009642006
A35: Christensen B.E.; Cline B.N.; Lundstrom N.G.; Yore A.S. | B35: Christensen, Brant E. (54987433400); Cline, Brandon N. (36598104200); Lundstrom, Nathan G. (57220897729); Yore, Adam S. (56003709500) | C35: 54987433400; 36598104200; 57220897729; 56003709500 | D35: Do Auditors View Off-the-Clock Misbehavior by Company Leadership as a Signal of Tone at the Top? | E35: 2024 | F35: Accounting Review | G35: 99 | H35: 5 | J35: 171 | K35: 196 | L35: 1 | M35: 10.2308/TAR-2021-0026 | N35: https://www.scopus.com/inward/record.uri?eid=2-s2.0-85203412911&doi=10.2308%2FTAR-2021-0026&partnerID=40&md5=177573021ba3860c9fa2310154b39c55 | O35: We study off-the-clock indiscretion accusations against corporate officers and directors and examine the extent, effectiveness, and context of auditors’ response. In the year that indiscretion allegations are first publicized, auditors charge higher fees and are more likely to resign. Auditors respond to allegations against both top executives and board members. Further, reactions are strongest when allegations demonstrate a lack of individual integrity and, separately, when the audit office has previously audited other similarly accused clients. Importantly, the resulting increase in auditors’ effort partially negates the association between indiscretions and lower financial reporting quality. However, auditors are primarily reactive, rather than proactive, and their response is stronger when the accused client is less important economically. These results suggest that company leadership’s off-the-clock indiscretions are signals to auditors of poor tone at the top, but the audit response is not uniform across all clients. © 2024 American Accounting Association. All rights reserved. | P35: auditor; indiscretions; integrity; risk; tone at the top | R35: Article | S35: Final | T35: All Open Access; Bronze Open Access | U35: Scopus | V35: 2-s2.0-85203412911
A36: Lee S.S.; Ling Z.; Rezaee Z. | B36: Lee, Sam Sunghan (54583906200); Ling, Zhejia (55606736900); Rezaee, Zabihollah (6603153872) | C36: 54583906200; 55606736900; 6603153872 | D36: Securities and Exchange Commission Comment Letter Disclosures and Short Sellers' Front Running | E36: 2023 | F36: Accounting Review | G36: 98 | H36: 5 | J36: 375 | K36: 400 | L36: 10 | M36: 10.2308/TAR-2017-0690 | N36: https://www.scopus.com/inward/record.uri?eid=2-s2.0-85171647248&doi=10.2308%2FTAR-2017-0690&partnerID=40&md5=e44f824722553f5f47814d8208256d03 | O36: Prior studies show that comment letters released by the Securities and Exchange Commission provide information on firms' financial reporting quality and can have adverse value implications about the firms. We examine whether short sellers front-run comment letter disclosures and take short positions based on the economic implications of the letters. We find that short interest increases before comment letter disclosures and that the increase is positively associated with the severity of the letters. We also find evidence suggesting that short sellers obtain private information through social connections with corporate insiders. Finally, we document a negative but delayed market reaction to the disclosure of severe comment letters. These results suggest that front running the comment letter disclosure is not the optimal trading strategy for short sellers. Short sellers can gain similar profits, and bear less risk, if they put off increasing their short positions until after the disclosure. © 2023 American Accounting Association. All rights reserved. | P36: SEC comment letters; short selling; social connections | R36: Article | S36: Final | U36: Scopus | V36: 2-s2.0-85171647248
A37: Donnelly A.M.; Donnelly D.P. | B37: Donnelly, Amy M. (57269675900); Donnelly, David P. (22984588000) | C37: 57269675900; 22984588000 | D37: A Systematic Review of Experimental Research on Accountability in Auditing | E37: 2023 | F37: Accounting Review | G37: 35 | H37: 3 | L37: 0 | M37: 10.2308/BRIA-2021-050 | N37: https://www.scopus.com/inward/record.uri?eid=2-s2.0-85173736043&doi=10.2308%2FBRIA-2021-050&partnerID=40&md5=c9a047f99b8f4bb90b9b011041aa97e5 | O37: Accountability research in auditing has spanned several decades, highlighting its importance in better understanding auditors’ judgments and decision-making processes. This study provides a systematic review of experimental audit research on accountability. We identify how previous research findings relate to theory, offer design considerations for future research, and provide future research opportunities. Relevant research was identified utilizing two databases. After removing duplicate records and applying exclusion criteria, a final population of 47 manuscripts is included in this review. We find that prior research results largely align with Tetlock’s social contingency model of accountability. This research stream is ripe with opportunities to enhance our understanding of accountability in auditing. Avenues for future research include investigating auditors’ responses to multiple accountability pressures, developing a measure of accountability, better understanding accountability in a post-COVID work environment, and considering ways to improve audit quality by shifting from a punitive to a more rewards-based system. © 2023 American Accounting Association. All rights reserved. | P37: accountability; auditing; experimental; literature review | R37: Review | S37: Final | U37: Scopus | V37: 2-s2.0-85173736043
A38: Asay H.S.; Hoopes J.L.; Thornock J.R.; Wilde J.H. | B38: Asay, H. Scott (57201008854); Hoopes, Jeffrey L. (35272099300); Thornock, Jacob R. (37125061600); Wilde, Jaron H. (56117428300) | C38: 57201008854; 35272099300; 37125061600; 56117428300 | D38: Tax Boycotts | E38: 2024 | F38: Accounting Review | G38: 99 | H38: 1 | J38: 1 | K38: 29 | L38: 15 | M38: 10.2308/TAR-2021-0213 | N38: https://www.scopus.com/inward/record.uri?eid=2-s2.0-85190977095&doi=10.2308%2FTAR-2021-0213&partnerID=40&md5=3ede8196e331acbdce2f7424963e43c9 | O38: To what extent do U.S. consumers change their purchase behavior or, in the extreme, boycott companies based on negative information about corporate tax activities? Practitioner publications and academic research identify consumers as a key corporate tax stakeholder. But we have limited empirical evidence whether information about corporate tax activities influences consumer actions. We undertake a comprehensive study of this question, triangulating across several settings. First, a representative sample of consumers suggests they rarely boycott in response to corporate tax activities. Next, an analysis of granular retail scanner data fails to provide compelling evidence of consumer purchase responses to negative tax news. An analysis of individual foot traffic at retail establishments around negative tax news again fails to suggest U.S. consumers change their shopping activities in response to negative tax news. The combined evidence suggests consumers do not meaningfully alter their purchase behavior in response to negative tax news. © 2024 American Accounting Association. All rights reserved. | P38: boycotts; consumers; corporate reputation; tax planning | R38: Article | S38: Final | U38: Scopus | V38: 2-s2.0-85190977095
A39: Espahbodi R.; Lin J.; Liu N.; Mock T.J.; Song M. | B39: Espahbodi, Reza (6506166072); Lin, Jiarong (58510857800); Liu, Nan (56895468200); Mock, Theodore J. (7004198554); Song, Mohan (58511213000) | C39: 6506166072; 58510857800; 56895468200; 7004198554; 58511213000 | D39: The Effect of Reporting Key Audit Matters on Audit Fees and Financial Reporting Quality: Evidence from Hong Kong | E39: 2023 | F39: Accounting Review | G39: 35 | H39: 3 | L39: 0 | M39: 10.2308/JIAR-2021-045 | N39: https://www.scopus.com/inward/record.uri?eid=2-s2.0-85173790946&doi=10.2308%2FJIAR-2021-045&partnerID=40&md5=680aa3bf73c21237d71e8007da507566 | O39: In 2015, the Hong Kong Institute of Certified Public Accountants issued a standard requiring auditors to communicate key audit matters (KAMs) in the audit report. This standard provides an opportunity to examine the effect of KAMs on audit fees and financial reporting quality. Using public companies listed on the Main Board of the Hong Kong Stock Exchange as the treatment group and the companies listed on the Shanghai and Shenzhen Main Board Stock Exchanges as the control group, pre-post and difference-in-differences analyses show that the KAMs standard resulted in improved financial reporting quality but also higher audit fees. Further analyses show that, although the increase in audit fees was related to the risk of material financial statement mis-statements and audit firm business risk, the improvement in financial reporting, which occurred for companies with low financial reporting quality, resulted from the “threat to management of disclosure in KAMs.” © 2023 American Accounting Association. All rights reserved. | P39: accruals; audit fees; audit quality; auditing standards; financial reporting quality; key audit matters | R39: Article | S39: Final | U39: Scopus | V39: 2-s2.0-85173790946
A40: Li M.; Markov S.; Shu S. | B40: Li, Meng (58605795100); Markov, Stanimir (7006357914); Shu, Susan (8697034100) | C40: 58605795100; 7006357914; 8697034100 | D40: Motivational Optimism and Short-Term Investment Efficiency | E40: 2023 | F40: Accounting Review | G40: 98 | H40: 5 | J40: 429 | K40: 454 | L40: 8 | M40: 10.2308/TAR-2018-0388 | N40: https://www.scopus.com/inward/record.uri?eid=2-s2.0-85171680297&doi=10.2308%2FTAR-2018-0388&partnerID=40&md5=b29defe927724b27eca9ce944be3264b | O40: We explore whether managers' strong desire for good performance distorts their expectations and, consequently, corporate investment efficiency. We find that managers overweight favorable information and underweight unfavorable information, resulting in optimistic earnings guidance. We construct an ex ante measure of optimism and show that greater optimism is associated with a lower inventory investment efficiency: Managers overinvest in inventory, resulting in lower inventory turnover and increased incidence and severity of inventory writedowns. We also find motivational optimism influences firms' financial reporting and is associated with an increased incidence of financial misreporting. Our results are consistent with the psychology theory of motivated reasoning, which emphasizes the distortive effects of preferences on beliefs and judgments. © 2023 American Accounting Association. All rights reserved. | P40: corporate investments; financial misreporting; inventories; management forecasts; motivated reasoning; optimistic expectations | R40: Article | S40: Final | U40: Scopus | V40: 2-s2.0-85171680297
A41: Chen H.; Tang S.; Wu D.; Yang D. | B41: Chen, Hanwen (36642593200); Tang, Song (55449995700); Wu, Donghui (23390969100); Yang, Daoguang (57216454754) | C41: 36642593200; 55449995700; 23390969100; 57216454754 | D41: The political dynamics of corporate tax avoidance: The Chinese experience | E41: 2021 | F41: Accounting Review | G41: 96 | H41: 5 | J41: 157 | K41: 180 | L41: 126 | M41: 10.2308/TAR-2017-0601 | N41: https://www.scopus.com/inward/record.uri?eid=2-s2.0-85115148425&doi=10.2308%2FTAR-2017-0601&partnerID=40&md5=2448377000f2738e12e8630777fd35ef | O41: In China’s political selection system, officials capable of growing local economies are rewarded with promotions. Eager to demonstrate economic achievements, newly appointed local leaders may raise tax revenues to expand fiscal expenditures on infrastructure projects. Against this backdrop, we study how political appointments influence local firms’ tax planning. Based on a sample of locally administered state-owned enterprises (SOEs), we find that firms decrease their tax avoidance after new leaders take office. The political-turnover effect on these firms’ tax positions is more evident when the incoming leaders have more political clout over SOE managers, the incentives to divert resources are stronger, or politician-manager networks are present, and subsides following the launch of the anticorruption campaign. Furthermore, firms with higher post-turnover tax payments subsequently receive more government contracts or subsidies. Overall, our findings suggest political incentives shape the tax-planning activities of SOE managers in a ‘‘two-way favor exchange’’ manner. © 2021 American Accounting Association. All rights reserved. | P41: Agency problem; Political cycle; Tax avoidance | R41: Article | S41: Final | U41: Scopus | V41: 2-s2.0-85115148425
A42: Gipper B.; Hail L.; Leuz C. | B42: Gipper, Brandon (55960678600); Hail, Luzi (14021009400); Leuz, Christian (6602397487) | C42: 55960678600; 14021009400; 6602397487 | D42: On the economics of mandatory audit partner rotation and tenure: Evidence from PCAOB data | E42: 2021 | F42: Accounting Review | G42: 96 | H42: 2 | J42: 303 | K42: 331 | L42: 74 | M42: 10.2308/TAR-2018-0347 | N42: https://www.scopus.com/inward/record.uri?eid=2-s2.0-85104688826&doi=10.2308%2FTAR-2018-0347&partnerID=40&md5=f65e555ec5ab68e3928a5d74787072fe | O42: We analyze the effects of partner tenure and mandatory rotation on audit quality, pricing, and production for a large cross-section of U.S. public firms during 2008-2014. On average, we find no evidence that audit quality declines over the tenure cycle and little support for ''fresh-look'' benefits provided by the new audit partner. Audit fees decline and audit hours increase after mandatory rotation, but then reverse over the tenure cycle. We also find evidence that audit firms use ''shadowing'' in preparation for a lead partner turnover. These effects differ by competitiveness of the local audit market, client size, and partner experience. When multiple members of the audit team commence work at a new client, the transition appears to be more disruptive and more likely to exhibit audit quality effects. Our findings point to costly efforts by the audit firms to minimize disruptions and audit failures around mandatory rotations. © 2021 American Accounting Association. All rights reserved. | P42: Audit fees; Audit partner tenure; Audit quality; Auditing; Auditor rotation; Competition; PCAOB | R42: Article | S42: Final | U42: Scopus | V42: 2-s2.0-85104688826
A43: Kim E. | B43: Kim, Eunjee (59772404400) | C43: 59772404400 | D43: Does Disclosure Regulation Affect Mutual Fund Families’ Proxy Voting? | E43: 2025 | F43: Accounting Review | G43: 100 | H43: 3 | J43: 333 | K43: 361 | L43: 1 | M43: 10.2308/TAR-2022-0653 | N43: https://www.scopus.com/inward/record.uri?eid=2-s2.0-105004290783&doi=10.2308%2FTAR-2022-0653&partnerID=40&md5=f15443bfc032dcb46bf70214d55554e0 | O43: Nonactivist investors that own more than 5 percent of a firm must report their holdings by filing a 13G in which they must commit to not influencing control of the firm. Mutual fund families are the most common investors filing 13Gs. I study whether the 13G requirement affects mutual fund families’ voting in proxy contests. I find mutual fund families that file the form are less likely to vote for activist proposals than are those that do not, suggesting that the requirement discourages mutual fund families from supporting activists who seek to influence control of the firm. The effects strengthen when vote outcomes directly affect the firm’s control and when activists pose a higher threat to the firm. I further document that the aggregate voting power of 13G-filing mutual fund families correlates with management winning contested votes and retaining board seats during proxy contests. © 2025 American Accounting Association. All rights reserved. | P43: mutual funds; proxy contests; proxy voting; regulations; Schedule 13G | R43: Article | S43: Final | U43: Scopus | V43: 2-s2.0-105004290783
A44: Zhang V.Q. | B44: Zhang, Vincent Qiru (58834830900) | C44: 58834830900 | D44: Municipal Bond Credit Rating Access and Retail Investors’ Transaction Costs | E44: 2024 | F44: Accounting Review | G44: 99 | H44: 1 | J44: 427 | K44: 453 | L44: 2 | M44: 10.2308/TAR-2022-0180 | N44: https://www.scopus.com/inward/record.uri?eid=2-s2.0-85182937477&doi=10.2308%2FTAR-2022-0180&partnerID=40&md5=8fd77e16b359e3b530b5a656a692ae5c | O44: In 2010, the Municipal Securities Rulemaking Board proposed a rule change requiring the display of current credit ratings on the EMMA website, a centralized repository of municipal bond information. Before the rule change, current credit ratings were freely available on individual rating agencies’ websites or on EMMA if municipalities provided relevant continuing disclosures, making it unclear whether the rule change would benefit investors. A difference-in-differences analysis reveals the rule change is associated with a 6–8 basis-point decrease in investor transaction costs. This effect is concentrated among the intended beneficiaries (retail investors) when credit risk information demand is high (long-maturity bonds) and current credit rating information on EMMA is low (no continuing disclosure of rating changes was provided on EMMA). The rule change appears to have helped retail investors become aware of current credit ratings by filling a disclosure gap on EMMA for municipalities without continuing disclosures of rating changes. © 2024 American Accounting Association. All rights reserved. | P44: continuing disclosures; credit ratings; EMMA; MSRB; municipal bond market; processing costs; retail investors | R44: Article | S44: Final | U44: Scopus | V44: 2-s2.0-85182937477
A45: Bauer T.D.; Deore A.; Presslee A.; Shaw J. | B45: Bauer, Tim D. (55954315000); Deore, Aishwarrya (57262888300); Presslee, Adam (55516416100); Shaw, Joanna (60079946600) | C45: 55954315000; 57262888300; 55516416100; 60079946600 | D45: Reward Taxation, Reward Type, and Employee Effort | E45: 2025 | F45: Accounting Review | G45: 100 | H45: 5 | J45: 55 | K45: 80 | L45: 0 | M45: 10.2308/TAR-2023-0450 | N45: https://www.scopus.com/inward/record.uri?eid=2-s2.0-105014765695&doi=10.2308%2FTAR-2023-0450&partnerID=40&md5=525c7b705d2cc5abb415f1466010a4b9 | O45: Performance-contingent cash and tangible rewards are commonly used to motivate employees, and the taxation of such rewards is unavoidable. We use two experiments to examine how the effect of reward taxation on employee effort varies by reward type. In Experiment 1, we find reward taxation decreases positive affect, increases negative affect, and decreases reward attractiveness for employees when rewards are tangible, but not when rewards are cash. In Experiment 2, we find reward taxation reduces employee effort when rewards are tangible, but not when rewards are cash. Collectively, this evidence advances knowledge at the intersection of tax and management accounting by explaining why reward type alters the effect of reward taxation on employee effort. Moreover, our experimental results inform managers of a potential downside to using tangible rewards to motivate employees. © 2025 American Accounting Association. All rights reserved. | P45: affect; effort; reward attractiveness; reward taxation; tangible rewards | R45: Article | S45: Final | T45: All Open Access; Bronze Open Access | U45: Scopus | V45: 2-s2.0-105014765695
A46: Starica C.; Marton J.P. | B46: Starica, Catalin (57214576917); Marton, Jan P. (24734186000) | C46: 57214576917; 24734186000 | D46: Identifying the Relationship between Earnings and Prices | E46: 2025 | F46: Accounting Review | G46: 100 | H46: 2 | J46: 383 | K46: 420 | L46: 3 | M46: 10.2308/TAR-2023-0205 | N46: https://www.scopus.com/inward/record.uri?eid=2-s2.0-86000142354&doi=10.2308%2FTAR-2023-0205&partnerID=40&md5=ce44653a7a0e486d83ac8f67f080d2d3 | O46: The relationships between accounting earnings and stock prices, as well as between unexpected earnings and returns, have received substantial attention in the empirical literature. Several theoretical models predict the shapes of these relationships. However, a comprehensive empirical description that could be used to evaluate these predictions is lacking. By integrating recent advances in statistics and machine learning with findings in the accounting literature, we develop an empirical method to identify the relationships, which is consistent with the firm-specific and nonlinear features of the theoretical models. Our approach provides a clear description of stylized and robust patterns in the relationships that are relevant to distinguish between existing models and to aid future theory development. The findings are consistent with recently proposed dynamic option models for both the earnings-price and unexpected earnings-returns relationships. © 2025 American Accounting Association. All rights reserved. | P46: dynamic real options; earnings-price relation; investment-based models, conditional expectation; machine learning; nonlinear association; unexpected earnings-return relation | R46: Article | S46: Final | T46: All Open Access; Bronze Open Access | U46: Scopus | V46: 2-s2.0-86000142354
A47: Gold A.; Kadous K.; Leiby J. | B47: Gold, Anna (35573403800); Kadous, Kathryn (6603060315); Leiby, Justin (56040190200) | C47: 35573403800; 6603060315; 56040190200 | D47: Does Status Equal Substance? The Effects of Specialist Social Status on Auditor Assessments of Complex Estimates | E47: 2024 | F47: Accounting Review | G47: 99 | H47: 5 | J47: 197 | K47: 222 | L47: 2 | M47: 10.2308/TAR-2021-0298 | N47: https://www.scopus.com/inward/record.uri?eid=2-s2.0-85203407585&doi=10.2308%2FTAR-2021-0298&partnerID=40&md5=15baffe18fb7f702f7a0b4ac393f8123 | O47: Auditing standards require that auditors’ reliance on a specialist is commensurate with the specialist’s competence. In assessing competence, auditors encounter cues diagnostic of the specialist’s social status but less so of competence. In an experiment, we manipulate specialist status and find that auditors mistake status for competence unless they are prompted to separate the constructs. This raises the possibility that auditors could over-rely on high-status specialists. However, auditors also assess high-status specialists as more influential, and when the specialist disagrees with the client, they rely more on high-status specialists because of this perceived influence. Thus, high-status specialists can increase auditors’ willingness to challenge the client by providing a strong ally. Additional analyses suggest that auditors are aware that they rely on the specialist’s influence rather than competence, indicating that auditors do not use the process that auditing standards envision to evaluate and rely on specialists. © 2024 American Accounting Association. All rights reserved. | P47: advice; auditing complex estimates; specialists; status | R47: Article | S47: Final | T47: All Open Access; Green Open Access | U47: Scopus | V47: 2-s2.0-85203407585
A48: Brown N.C.; Huffman A.A.; Cohen S. | B48: Brown, Nerissa C. (37460989800); Huffman, Adrienna A. (57078264700); Cohen, Shira (57269566100) | C48: 37460989800; 57078264700; 57269566100 | D48: Accounting Reporting Complexity and Non-GAAP Earnings Disclosure | E48: 2023 | F48: Accounting Review | G48: 98 | H48: 6 | J48: 37 | K48: 71 | L48: 19 | M48: 10.2308/TAR-2018-0760 | N48: https://www.scopus.com/inward/record.uri?eid=2-s2.0-85174960380&doi=10.2308%2FTAR-2018-0760&partnerID=40&md5=98c5bd3ffca4266d4964e1f070951243 | O48: We examine whether the complexity of mandatory accounting disclosures prompts managers to voluntarily disclose adjusted measures of actual earnings performance, and whether this practice reflects attempts to obfuscate or mitigate the informational opacity accounting complexity creates for investors. Using the metadata in XBRL filings, we construct measures of accounting complexity that map directly to the mandated standards applied in financial statement filings. We find a positive and economically significant association between accounting complexity and managers’ propensity to disclose non-GAAP earnings information. This relation is robust and incremental to common measures of business and linguistic complexity, and the transitory nature of firms’ economic activities. We also find that the quality and informativeness of adjusted earnings information increases with accounting complexity, consistent with motives to better inform investors when accounting disclosures are complex. Overall, our results suggest that managers use non-GAAP earnings disclosure to mitigate the adverse informational effects of accounting complexity. © 2023 American Accounting Association. All rights reserved. | P48: accounting complexity; GAAP; non-GAAP earnings; voluntary disclosure; XBRL | R48: Article | S48: Final | U48: Scopus | V48: 2-s2.0-85174960380
A49: Kim T.W.; Li J.; Pae S. | B49: Kim, Tae Wook (57193520924); Li, Jing (57191831877); Pae, Suil (6701609709) | C49: 57193520924; 57191831877; 6701609709 | D49: Career Concerns, Investment, and Management Forecasts | E49: 2023 | F49: Accounting Review | G49: 98 | H49: 1 | J49: 337 | K49: 363 | L49: 3 | M49: 10.2308/TAR-2019-0272 | N49: https://www.scopus.com/inward/record.uri?eid=2-s2.0-85165661431&doi=10.2308%2FTAR-2019-0272&partnerID=40&md5=38ca34fe63eb128d814cb0a9a8fa3648 | O49: A firm manager is concerned about both the firm value and the market assessments of his abilities. When investing in a project, he has private knowledge of his project-related ability that interacts with the project investment, and his general ability that produces a cash flow independent of the project cash flow. The concerns about the general (project-related) ability assessment create a signaling incentive to decrease (increase) investment. In the presence of underinvestment (overinvestment), higher-quality earnings information reduces (improves) equilibrium efficiency. When the manager issues an earnings forecast as an additional signaling device, the forecast is upwardly biased, and the equilibrium investment is smaller than that without a forecast. The latter is because the signaling incentive to decrease investment is strengthened. When the manager’s concerns about the general ability assessment are relatively large, he is better off by committing to no forecast. Novel empirical predictions about investment and earnings forecast emerge. © 2023 American Accounting Association. All rights reserved. | P49: career concerns; earnings forecast; efficiency; investment | R49: Article | S49: Final | U49: Scopus | V49: 2-s2.0-85165661431
A50: Diller M.; Lorenz J.; Schneider G.; Sureth-Sloane C. | B50: Diller, Markus (57189364127); Lorenz, Johannes (57057050800); Schneider, Georg (55057824100); Sureth-Sloane, Caren (6507559294) | C50: 57189364127; 57057050800; 55057824100; 6507559294 | D50: Is Tax Transfer Pricing Harmonization a Panacea? Real Effects of Global Tax Transparency and Standards Consistency | E50: 2025 | F50: Accounting Review | G50: 100 | H50: 2 | J50: 71 | K50: 102 | L50: 6 | M50: 10.2308/TAR-2021-0477 | N50: https://www.scopus.com/inward/record.uri?eid=2-s2.0-86000177314&doi=10.2308%2FTAR-2021-0477&partnerID=40&md5=ca136e4c2150ddfd682e90e2d22cc6d3 | O50: This study investigates the impact of the harmonization of tax transfer pricing across jurisdictions on multinational companies’ reporting and tax authorities’ auditing strategies. Applying a game-theoretical approach, we assess how enhancing standards consistency and global tax transparency influences tax avoidance and double taxation, producer and consumer surplus, and countries’ tax revenue. Although increasing transparency is generally perceived to discourage tax avoidance, we show that this effect vanishes when standards are inconsistent. We demonstrate that high global tax transparency and consistent standards maximize global social welfare. However, from the perspective of multinational companies or individual countries, the optimal mix of consistency and transparency may differ. These findings highlight why transfer pricing harmonization is difficult and how single-player incentives undermine the envisioned benefits of tax harmonization. This study offers valuable insights for policymakers who aim to curb tax avoidance and mitigate the risk of double taxation. © 2025 American Accounting Association. All rights reserved. | P50: real effects; standards inconsistency; tax avoidance; tax harmonization; tax transparency; transfer pricing | R50: Article | S50: Final | U50: Scopus | V50: 2-s2.0-86000177314
A51: Alhusaini B.; Lamoreaux P.T.; Newton N.J. | B51: Alhusaini, Badryah (57226606019); Lamoreaux, Phillip T. (56539692600); Newton, Nathan J. (55805174700) | C51: 57226606019; 56539692600; 55805174700 | D51: IPOs and Auditor Reputation: Evidence from Audit Firm Data Breaches | E51: 2025 | F51: Accounting Review | G51: 100 | H51: 5 | J51: 1 | K51: 25 | L51: 0 | M51: 10.2308/TAR-2023-0417 | N51: https://www.scopus.com/inward/record.uri?eid=2-s2.0-105015062752&doi=10.2308%2FTAR-2023-0417&partnerID=40&md5=ec95904ab3d841b27823a4f902a5800a | O51: We use audit firm data breaches as time-varying, reputation-harming events to examine the value of auditor reputation—independent of actual audit quality—in the IPO process. We find that auditor data breaches are negatively associated with IPO offer price revisions. We demonstrate that this effect is due to an increase in institutional investors’ perception of information risk. Specifically, the effect is mitigated when other parties involved in the IPO reduce information risk themselves and when institutional investors are less likely to rely on audited financial information. In additional tests, we find that the impact of breaches on IPO offer price revisions is concentrated in breaches with greater severity, saliency, and frequency, consistent with institutional investors reacting to the announcement of the data breach rather than some other confounding factor. Collectively, our evidence suggests that IPO investors perceive time-varying reputational value of the external auditor, independent of changes in audit quality. © 2025 American Accounting Association. All rights reserved. | P51: auditor reputation; data breaches; initial public offerings | R51: Article | S51: Final | U51: Scopus | V51: 2-s2.0-105015062752
A52: Chen X.; Li N.; Lin A.-P. | B52: Chen, Xia (57211452240); Li, Na (57258269600); Lin, An-Ping (57188806021) | C52: 57211452240; 57258269600; 57188806021 | D52: CFO Gaps: Determinants and Impact on the Corporate Information Environment | E52: 2022 | F52: Accounting Review | G52: 97 | H52: 6 | J52: 173 | K52: 200 | L52: 6 | M52: 10.2308/TAR-2019-0001 | N52: https://www.scopus.com/inward/record.uri?eid=2-s2.0-85143072781&doi=10.2308%2FTAR-2019-0001&partnerID=40&md5=0a45dbda846e10d86df33ba4d45cb682 | O52: A CFO gap arises when the CFO position is left vacant for a period between the departure of the old CFO and the appointment of a new CFO. We find that CFO gaps are fairly common; over the sample period 2004–2016, approximately one-third of CFO turnovers are associated with a CFO gap, lasting, on average, two quarters and two months. CFO gaps are more likely for firms that face more labor market search frictions and with financial reporting and performance issues, and are less likely for firms with succession plans and with greater growth opportunities. While CFO gaps are not associated with significant changes in firms’ financial reporting quality, they are associated with significantly negative changes in firms’ voluntary disclosure frequency and analysts’ forecast quality. Our findings shed light on the factors that influence top executive gaps and the impact of such gaps on firms’ information environment. © 2022 American Accounting Association. All rights reserved. | P52: CFO gaps; CFO turnovers; information environment | R52: Article | S52: Final | U52: Scopus | V52: 2-s2.0-85143072781
A53: Davidson R.H.; Pirinsky C. | B53: Davidson, Robert H. (55823452400); Pirinsky, Christo (21835084100) | C53: 55823452400; 21835084100 | D53: The Deterrent Effect of Insider Trading Enforcement Actions | E53: 2022 | F53: Accounting Review | G53: 97 | H53: 3 | J53: 227 | K53: 247 | L53: 21 | M53: 10.2308/TAR-2020-0003 | N53: https://www.scopus.com/inward/record.uri?eid=2-s2.0-85136543389&doi=10.2308%2FTAR-2020-0003&partnerID=40&md5=c4b20bf72d31cd8e2e95fa1a209478e9 | O53: We analyze whether exposure to an SEC insider trading enforcement action affects how insiders trade. We find that following an insider trading enforcement action at one firm, exposed insiders earn significantly lower abnormal profits from their trades at other firms compared to non-exposed insiders. The deterrent effect is stronger when a fellow insider is convicted, and is similarly significant both pre- and post-SOX. Following the enforcement event, exposed insiders do not trade less frequently, but do trade significantly fewer shares per trade. Insiders who have witnessed an enforcement action have a lower probability for future conviction than their unexposed peers. © 2022 American Accounting Association. All rights reserved. | P53: deterrence; enforcement; inside information; insider trading; salience | R53: Article | S53: Final | U53: Scopus | V53: 2-s2.0-85136543389
A54: Cunningham L.M.; Ereddia L.E. | B54: Cunningham, Lauren M. (57125612700); Ereddia, Laurie E. (58236227600) | C54: 57125612700; 58236227600 | D54: Attracting Female Directors in the United States: The Roles of Boards, Executives, and Other Stakeholders | E54: 2023 | F54: Accounting Review | G54: 35 | H54: 3 | L54: 0 | M54: 10.2308/JIAR-2021-096 | N54: https://www.scopus.com/inward/record.uri?eid=2-s2.0-85173762881&doi=10.2308%2FJIAR-2021-096&partnerID=40&md5=7b1a3512f3d8e32a02f3c8123c309e29 | O54: Previous research related to board gender diversity typically focuses on international settings outside of the U.S. In this study, we examine the influence of boards, executives, and other stakeholders in appointing a female director candidate to a U.S. board, which is a voluntary regime dominated by male candidates. Following institutional theory, social identity theory, and resource dependence theory, we find that boards, executives, and institutional investors play persistent roles across various time periods, company sizes, and levels of CEO power. Workforce and customer stakeholders have become significant influencers only in more recent years and in smaller firms. Understanding factors that allow firms to successfully attract female board members in a voluntary regime should be of interest to board members and regulators worldwide. Our findings should also be of interest to accounting academics examining the role of board gender diversity in the oversight of audit, financial reporting, and tax policies. © 2023 American Accounting Association. All rights reserved. | P54: board composition; board of directors; female directors; gender diversity; stakeholders | R54: Article | S54: Final | U54: Scopus | V54: 2-s2.0-85173762881
A55: Lin Y.-H.; Huang T.-C. | B55: Lin, Yi-Hung (56199071500); Huang, Ting-Chiao (56381786600) | C55: 56199071500; 56381786600 | D55: Does Regulatory Reform of Internal Controls in China Improve Internal Control Effectiveness? Role of Corporate Social Responsibility Engagement | E55: 2023 | F55: Accounting Review | G55: 35 | H55: 3 | L55: 0 | M55: 10.2308/JIAR-2021-044 | N55: https://www.scopus.com/inward/record.uri?eid=2-s2.0-85173762760&doi=10.2308%2FJIAR-2021-044&partnerID=40&md5=973ca1d8d13231c3722a2b787e09d765 | O55: The regulatory reform of internal controls (ICs) in China mandates that certain firms incorporate corporate social responsibility (CSR) engagement into ICs and issue IC reports. Using a staggered difference-in-differences research design, we find that IC effectiveness has worsened following this reform, but this deterioration is partially mitigated when mandated firms report their CSR engagement. Additional analyses demonstrate that this deterioration is further lessened when CSR reports are prepared in accordance with Global Reporting Initiative reporting guidelines or assured by external auditors and when firms spend more on CSR activities. Finally, cross-sectional analyses suggest that CSR engagement mitigates the deterioration in IC effectiveness more in non–state-owned enterprises and in firms that have better financial performance, lack political connections, or are located in regions with higher market development or social trust. © 2023 American Accounting Association. All rights reserved. | P55: China; corporate social responsibility; internal control; reform | R55: Article | S55: Final | U55: Scopus | V55: 2-s2.0-85173762760
A56: Williams B.; Williams B.M. | B56: Williams, Braden (57192232813); Williams, Brian M. (57192913930) | C56: 57192232813; 57192913930 | D56: Real Effects of Financial Reporting on Innovation: Evidence from Tax Law and Accounting Standards | E56: 2022 | F56: Accounting Review | G56: 96 | H56: 6 | J56: 397 | K56: 425 | L56: 20 | M56: 10.2308/TAR-2018-0582 | N56: https://www.scopus.com/inward/record.uri?eid=2-s2.0-85132667956&doi=10.2308%2FTAR-2018-0582&partnerID=40&md5=89f72f768bcae460d30a9e078d54cb93 | O56: This study examines whether financial accounting standards moderate the effectiveness of tax policy. Specifically, we examine whether myopic managers' focus on short-term financial reporting reduces the effectiveness of tax subsidies that incentivize innovation. We employ a novel setting, the issuance of Financial Interpretation No. 48 (FIN 48), which changed the financial reporting for some important, yet uncertain, tax incentives to innovate. For firms most affected by the standard change, we find evidence of reduced investment in innovation, reduced sensitivity of investment to tax incentives, and reduced future innovative output. Consistent with earnings myopia, we find the effect is more pronounced in firms with higher levels of transient institutional ownership and newly vesting equity compensation. These results indicate financial reporting myopia has real effects on innovation and can reduce tax policy effectiveness. The results further suggest that tax policymakers should consider both financial reporting and cash flow incentives in designing policy. © 2022 American Accounting Association. All rights reserved. | P56: accounting standards; FIN 48; R&D; tax policy | R56: Article | S56: Final | U56: Scopus | V56: 2-s2.0-85132667956
A57: Chen J.; Dou Y.; Ryan S.G.; Zou Y. | B57: Chen, Jing (59512298200); Dou, Yiwei (56273698300); Ryan, Stephen G. (35574572600); Zou, Youli (56706771300) | C57: 59512298200; 56273698300; 35574572600; 56706771300 | D57: The Effect of the Current Expected Credit Loss Approach on Banks’ Lending during Stress Periods: Evidence from the COVID-19 Recession | E57: 2025 | F57: Accounting Review | G57: 100 | H57: 1 | J57: 113 | K57: 138 | L57: 8 | M57: 10.2308/TAR-2022-0275 | N57: https://www.scopus.com/inward/record.uri?eid=2-s2.0-85214911695&doi=10.2308%2FTAR-2022-0275&partnerID=40&md5=10baf612f537da6914bed26faa063110 | O57: In the wake of the financial crisis, policymakers expressed the concern that the incurred loss model delays loan loss recognition to economic stress periods and thereby exacerbates banks’ lending contraction during these periods. Addressing this concern, the FASB issued Accounting Standards Update 2016-13, which requires large public banks to accrue for loan losses using the current expected credit loss (CECL) approach starting in January 2020. We hypothesize and find that banks that adopted CECL prior to the COVID-19 pandemic increased loan loss provisions and reduced loan growth during the accompanying recession more than other banks. The lending contraction is stronger for adopting banks with low regulatory capital and low loan impairment and is primarily driven by commercial loans. Lastly, we find that counties in which CECL-adopting banks have higher market share experience larger increases in unemployment rates during the recession and slower subsequent recoveries. © 2025 American Accounting Association. All rights reserved. | P57: banks; COVID-19; current expected credit loss (CECL) approach; lending; loan loss provisions; recession; regulatory capital | R57: Article | S57: Final | U57: Scopus | V57: 2-s2.0-85214911695
A58: Fuller S.H.; Joe J.R.; Luippold B.L. | B58: Fuller, Stephen H. (57320982300); Joe, Jennifer R. (7005313926); Luippold, Benjamin L. (55216590800) | C58: 57320982300; 7005313926; 55216590800 | D58: The Effect of Auditor Reporting Choice and Audit Committee Oversight on Management Financial Disclosures | E58: 2022 | F58: Accounting Review | G58: 96 | H58: 6 | J58: 239 | K58: 274 | L58: 26 | M58: 10.2308/TAR-2016-0246 | N58: https://www.scopus.com/inward/record.uri?eid=2-s2.0-85130069474&doi=10.2308%2FTAR-2016-0246&partnerID=40&md5=9581f56250b41f3b140fa792b66edda1 | O58: We investigate the joint effects of auditors' reporting choice and audit committee effectiveness on management disclosures about complex estimates. A new PCAOB standard requires auditors to report on Critical Audit Matters (CAMs): issues "communicated or required to be communicated to the audit committee" about accounts or disclosures that (1) "are material to the financial statements," and (2) "involved especially challenging, subjective, or complex auditor judgment" (PCAOB 2017a, 11). Consistent with investor arguments, we find that audit committee effectiveness and more detailed CAM reporting encourage managers' disclosures of the risk underlying complex estimates. When the auditor's report is more informative about a complex estimate and the audit committee is more effective, management's related financial disclosures are more forthcoming. However, less informative auditor disclosures or more effective audit committees alone do not prompt greater management disclosure. Thus, expanded auditor reporting and more effective audit committees, together, can enhance the disclosures investors value. © 2022 American Accounting Association. All rights reserved. | P58: audit committee oversight; auditor reporting; critical audit matters; expanded auditor's reports; extended auditor's reports; information risk; key audit matters; management disclosure; risk disclosure; voluntary disclosure | R58: Article | S58: Final | U58: Scopus | V58: 2-s2.0-85130069474
A59: Kachelmeier S.J.; Rimkus D. | B59: Kachelmeier, Steven J. (6506220075); Rimkus, Dan (57218670104) | C59: 6506220075; 57218670104 | D59: Does Seeking Audit Evidence Impede the Willingness to Impose Audit Adjustments? | E59: 2022 | F59: Accounting Review | G59: 97 | H59: 7 | J59: 269 | K59: 293 | L59: 4 | M59: 10.2308/TAR-2019-0613 | N59: https://www.scopus.com/inward/record.uri?eid=2-s2.0-85144086296&doi=10.2308%2FTAR-2019-0613&partnerID=40&md5=addf38184efb57a3124f1d8261b16006 | O59: In two incentivized auditing experiments, participants who choose to acquire evidence adjust for the risk revealed by that evidence to a lesser extent than those who obtain the same evidence without investigative action, controlling for the diagnostic value of evidence. This finding follows from mental accounting and information choice theories that, in combination, predict that choosing to undertake effortful investigation can magnify aversion to costly adjustments. In our first experiment, effort choice reduces adjustments only when the same participants make both decisions, not when different participants make these decisions in noninteractive pairs. We observe consistent findings in a second experiment that pairs all participants and allows interaction, with effort choice reducing adjustments only when participants responsible for evidence perceive high involvement in the adjustment decisions made by their paired counterparts. A potential implication of our study is that emerging audit technologies that facilitate evidence collection could also enhance auditor independence. © 2022 American Accounting Association. All rights reserved. | P59: audit adjustments; audit effort; audit technology; auditor independence; information choice; mental accounting | R59: Article | S59: Final | U59: Scopus | V59: 2-s2.0-85144086296
A60: Arnold M.C.; Artz M.; Tafkov I.D. | B60: Arnold, Markus C. (8889409700); Artz, Martin (55242015400); Tafkov, Ivo D. (36162114100) | C60: 8889409700; 55242015400; 36162114100 | D60: The Effect of Past Performance and Task Type on Managers' Target Setting Decisions: An Experimental Investigation | E60: 2022 | F60: Accounting Review | G60: 97 | H60: 7 | J60: 1 | K60: 22 | L60: 7 | M60: 10.2308/TAR-2021-0103 | N60: https://www.scopus.com/inward/record.uri?eid=2-s2.0-85144089440&doi=10.2308%2FTAR-2021-0103&partnerID=40&md5=f3403ffa2522ef745bf9bad41dfc0d5e | O60: We investigate how performance-to-target (exceeding versus missing prior target) and task type (ability-driven versus effort-driven) affect managers' target-setting decisions in a setting where a manager sets targets for multiple employees. To do so, we use an experiment that involves executives, who average more than 16 years of work experience. We predict and find stronger target adjustments when prior targets are exceeded than when they are missed, especially when tasks are ability-driven. We also predict and find targets are differentiated more between employees within a firm when tasks are ability-driven rather than effort-driven, but this effect is attenuated when prior targets are missed. As prior empirical findings are inconclusive in this area of research, we contribute to the literature by providing controlled experimental evidence about the asymmetric nature of target adjustments. Additionally, we identify an important factor affecting managers' target-setting decisions-task type-that has largely been neglected in prior work. © 2022 American Accounting Association. All rights reserved. | P60: performance-to-target; target adjustments; target difference; target setting; task type | R60: Article | S60: Final | U60: Scopus | V60: 2-s2.0-85144089440
A61: Zheng X. | B61: Zheng, Xin (57221555607) | C61: 57221555607 | D61: A Tale of Two Enforcement Venues: Determinants and Consequences of the SEC's Choice of Enforcement Venue After the Dodd-Frank Act | E61: 2022 | F61: Accounting Review | G61: 96 | H61: 6 | J61: 451 | K61: 476 | L61: 11 | M61: 10.2308/TAR-2018-0148 | N61: https://www.scopus.com/inward/record.uri?eid=2-s2.0-85112583513&doi=10.2308%2FTAR-2018-0148&partnerID=40&md5=a2126ae3805b8134a5f248ac0f1bb47c | O61: The Dodd-Frank Act allows the SEC to choose either an administrative proceeding or a federal court as an enforcement venue for resolving violations of federal securities laws. I examine determinants and consequences of the SEC's choice of enforcement venue after the Dodd-Frank Act. Results show that material cases are 28-35 percent more likely to be assigned to federal courts, and politically connected defendants are about 14 percent more likely to be routed to administrative proceedings. While monetary penalties by venue are statistically indifferent, politically connected defendants in administrative proceedings are associated with lower penalties. Additionally, I find that administrative proceedings process cases 27 times faster than federal courts. Results suggest the SEC's private incentives affect enforcement venue selection and possibly enforcement outcomes. The SEC is more likely to use administrative proceedings when political and economic costs are greater, and use federal courts when political and economic benefits are greater. © 2022 American Accounting Association. All rights reserved. | P61: Dodd-Frank Act; political connections; public enforcement; SEC administrative proceedings; SEC enforcement; securities litigation | R61: Article | S61: Final | U61: Scopus | V61: 2-s2.0-85112583513
A62: Gao J.; Merkley K.J.; Pacelli J.; Schroeder J.H. | B62: Gao, Janet (57192198883); Merkley, Kenneth J. (38361902200); Pacelli, Joseph (57194078382); Schroeder, Joseph H. (55910247400) | C62: 57192198883; 38361902200; 57194078382; 55910247400 | D62: Do Internal Control Weaknesses Affect Firms’ Demand for Accounting Skills? Evidence from U.S. Job Postings | E62: 2023 | F62: Accounting Review | G62: 98 | H62: 3 | J62: 203 | K62: 228 | L62: 22 | M62: 10.2308/TAR-2020-0109 | N62: https://www.scopus.com/inward/record.uri?eid=2-s2.0-85162790904&doi=10.2308%2FTAR-2020-0109&partnerID=40&md5=24edffcc6860c775bd5a97a2164a3485 | O62: In this study, we examine whether firms respond to internal control weaknesses (ICWs) by requiring accounting-specific skills when hiring rank-and-file employees. Using unique data containing an extensive collection of job postings, we document significant increases in firms’ job postings that list accounting skills after the disclosure of an ICW. This effect is more pronounced for firms with better financial resources and when ICWs are more severe or personnel-related. In addition, our results extend to employees that are not specifically designated as accountants, suggesting a broader role for rank-and-file employees in influencing internal control quality. Finally, we find that increases in job postings with accounting skill requirements are associated with improvements in internal controls and a higher likelihood of ICW remediation. Overall, our findings shed new light on how firms respond to ineffective internal controls by increasing their emphasis on accounting skills in their workforce. © 2023 American Accounting Association. All rights reserved. | P62: accounting skills; human capital; internal control; job postings | R62: Article | S62: Final | U62: Scopus | V62: 2-s2.0-85162790904
A63: Schafhäutle S.G.; Veenman D. | B63: Schafhäutle, Sandra G. (57226196822); Veenman, David (37065263900) | C63: 57226196822; 37065263900 | D63: Crowdsourced Forecasts and the Market Reaction to Earnings Announcement News | E63: 2024 | F63: Accounting Review | G63: 99 | H63: 2 | J63: 421 | K63: 456 | L63: 4 | M63: 10.2308/TAR-2021-0055 | N63: https://www.scopus.com/inward/record.uri?eid=2-s2.0-85187922178&doi=10.2308%2FTAR-2021-0055&partnerID=40&md5=a254e840a0e0328f3d497736c0ed8ee8 | O63: This study examines whether crowdsourced forecasts of earnings and revenues help investors unravel bias in earnings announcement news, which is commonly derived from analyst forecasts. Our results suggest that investors, on average, understand and price the predictive signals reflected in crowdsourced forecasts about the bias in analyst-based earnings and revenue surprises. Using the staggered addition of firms to the Estimize platform, we find that crowdsourced coverage is associated with reductions in the mispricing of forecast bias and declines in earnings announcement premia. We further find some evidence that managers use income-increasing accruals to meet the crowdsourced forecast benchmark and that they respond to crowdsourced coverage through increased downward earnings and revenue guidance. Overall, we conclude that user-generated content on crowdsourced financial information platforms helps investors discount biases in traditional equity research and thereby better process the news in earnings announcements. © 2024 American Accounting Association. All rights reserved. | P63: crowdsourcing; earnings announcements; Estimize; forecast bias; market reactions; sell-side analysts | R63: Article | S63: Final | U63: Scopus | V63: 2-s2.0-85187922178
A64: Cazier R.A.; McMullin J.L.; Treu J.S. | B64: Cazier, Richard A. (37064369500); McMullin, Jeff L. (55949883700); Treu, John S. (57214729500) | C64: 37064369500; 55949883700; 57214729500 | D64: Are lengthy and boilerplate risk factor disclosures inadequate? an examination of judicial and regulatory assessments of risk factor language | E64: 2021 | F64: Accounting Review | G64: 96 | H64: 4 | J64: 131 | K64: 155 | L64: 42 | M64: 10.2308/TAR-2018-0657 | N64: https://www.scopus.com/inward/record.uri?eid=2-s2.0-85111532744&doi=10.2308%2FTAR-2018-0657&partnerID=40&md5=ea920770264078f20360b563135e1562 | O64: Although formal guidance instructs firms to avoid issuing lengthy and boilerplate risk factor disclosures, regulators and users of financial statements note these disclosures are excessively long and boilerplate. The persistence of these characteristics is surprising given that prior research finds that firms disclosing lengthy and boilerplate risk factors experience negative capital market consequences. We investigate two potential sources of firms' incentives to issue such disclosures by examining how judicial and regulatory assessments of firms' risk factor disclosures correlate with the disclosure length and boilerplate. Results suggest that lengthier and more boilerplate risk factor disclosures are less likely to be considered inadequate under judicial and regulatory review. Further analysis finds that when risk factor language is assessed as adequate in judicial review, industry peers borrow that language more frequently, and that judicial assessments of risk factor disclosures prompt industry peers to lengthen their risk factor disclosures. © 2021 American Accounting Association. All rights reserved. | P64: Boilerplate; Disclosure regulation; Litigation risk; Risk disclosure; SEC comment letters; Securities lawsuits | R64: Article | S64: Final | U64: Scopus | V64: 2-s2.0-85111532744
A65: Chen J.Z.; Li Z.; Mao T.; Yoon A. | B65: Chen, Jeff Zeyun (36642578300); Li, Zengquan (36606286500); Mao, Ting (59978946200); Yoon, Aaron (57191748081) | C65: 36642578300; 36606286500; 59978946200; 57191748081 | D65: Global versus Local ESG Ratings: Evidence from China | E65: 2025 | F65: Accounting Review | G65: 100 | H65: 4 | J65: 161 | K65: 192 | L65: 33 | M65: 10.2308/TAR-2022-0703 | N65: https://www.scopus.com/inward/record.uri?eid=2-s2.0-105009939186&doi=10.2308%2FTAR-2022-0703&partnerID=40&md5=d35ca11ac366c7a1f50cb7c6fe68a668 | O65: We compare the ESG ratings of MSCI, a global rater, with those of SINO, a local Chinese rater, to evaluate their effectiveness in capturing ESG risks within the Chinese context. Using ESG issues revealed in negative incidents as a proxy for ESG risk, we find that the ratings from the two raters often diverge, with SINO generally outperforming MSCI in predicting ESG risks in China. This divergence is more pronounced for firms with extensive ESG disclosures and when there are significant differences in how the raters define and measure ESG issues. Distance-based information asymmetry does not appear to play a significant role in explaining the performance gap. The advantage of local raters likely stems from their flexibility in tailoring methodologies to reflect country-specific nuances. In contrast, global raters adopt consistent methodologies to meet investor demand for comparability, but this approach may inadvertently reduce their relevance for capturing localized ESG risks. © 2025 American Accounting Association. All rights reserved. | P65: China; ESG ratings; ESG risks; global versus local | R65: Article | S65: Final | T65: All Open Access; Bronze Open Access | U65: Scopus | V65: 2-s2.0-105009939186
A66: Lisic L.L.; Liu Q.; Seidel T.A.; Shi H.; Wang A.; Zimmerman A. | B66: Lisic, Ling Lei (50161996600); Liu, Qiliang (57191058333); Seidel, Timothy A. (56592166800); Shi, Hanzhong (57262281800); Wang, Angie (57226188732); Zimmerman, Aleksandra (56605326100) | C66: 50161996600; 57191058333; 56592166800; 57262281800; 57226188732; 56605326100 | D66: Common Auditors in Supply Chain Relationships and the Provision of Trade Credit | E66: 2026 | F66: Accounting Review | G66: 101 | H66: 1 | J66: 411 | K66: 435 | L66: 0 | M66: 10.2308/TAR-2022-0142 | N66: https://www.scopus.com/inward/record.uri?eid=2-s2.0-105030286542&doi=10.2308%2FTAR-2022-0142&partnerID=40&md5=b4b79ac57818e4ce092b760e099d702c | O66: This study examines the association between a shared common auditor among suppliers and customers and trade credit. Using hand-collected pairwise trade credit data, we find that a supplier extends more trade credit to a customer audited by a common auditor. This association is robust to alternative design specifications and various sample restrictions to alleviate selection bias. We then interview trade credit managers and executives as a prelude to archival analyses exploring multiple potential mechanisms to explain this association. The collective results are most consistent with the explanation that mutual third parties to a dyadic relationship can foster trust through social connections and increased salience of reputation effects rather than that a common auditor reduces information asymmetry about the rigor of the audit process. © 2026, American Accounting Association. All rights reserved. | P66: common auditor; intermediaries; operations; supply chain; trade credit | R66: Article | S66: Final | T66: All Open Access; Bronze Open Access | U66: Scopus | V66: 2-s2.0-105030286542
A67: Livdan D.; Nezlobin A. | B67: Livdan, Dmitry (6602627828); Nezlobin, Alexander (54895775300) | C67: 6602627828; 54895775300 | D67: Incentivizing Irreversible Investment | E67: 2022 | F67: Accounting Review | G67: 97 | H67: 1 | J67: 349 | K67: 371 | L67: 1 | M67: 10.2308/TAR-2017-0573 | N67: https://www.scopus.com/inward/record.uri?eid=2-s2.0-85127577762&doi=10.2308%2FTAR-2017-0573&partnerID=40&md5=cbd8d98899fbb99d29aa0991121ade2a | O67: Existing dynamic investment models that show that a manager can be incentivized to implement the optimal investment policy rely on the assumption that the firm is operating in an ever-expanding product market. This paper presents an analytically tractable, discrete-time, neoclassical model with irreversible investment and the possibility of unfavorable demand events. We show that even when the principal is uninformed about changes in demand for the firm's output, there exists a performance measurement system that leads to goal congruent investment incentives for the manager. If the principal can observe the unfavorable demand events, then goal congruence can be achieved using very simple accrual accounting rules, such as straight-line depreciation. © 2022 American Accounting Association. All rights reserved. | P67: goal congruence; irreversible investment; performance measurement; residual income | R67: Article | S67: Final | U67: Scopus | V67: 2-s2.0-85127577762
A68: Cahan S.F.; Chen C.; Chen L. | B68: Cahan, Steven F. (7003594466); Chen, Chen (56742693300); Chen, Li (36695857300) | C68: 7003594466; 56742693300; 36695857300 | D68: In Financial Statements We Trust: Institutional Investors' Stockholdings after Restatements | E68: 2024 | F68: Accounting Review | G68: 99 | H68: 2 | J68: 143 | K68: 168 | L68: 11 | M68: 10.2308/TAR-2019-0654 | N68: https://www.scopus.com/inward/record.uri?eid=2-s2.0-85187690921&doi=10.2308%2FTAR-2019-0654&partnerID=40&md5=57e8dd5577c36a4e2b5c92e2a0a40b23 | O68: How prior trust moderates investor responses to restatements is unknown. We examine how societal trust affects the changes in institutional investors' shareholdings around a restatement. We consider two competing hypotheses based on the erosion of trust and confirmatory bias. We find the change in institutional investors' shareholdings around a restatement is more negative for investors from high trust areas compared to low trust areas, consistent with an erosion of trust where high trust institutional investors view the restatement as a violation of trust. Further analyses show that our findings vary with the regulatory or economic environment, type of institution, and type of restatement. Our results are also robust to different tests that address endogeneity and use alternative societal trust measures. Overall, we contribute to the literature by examining the role of societal trust in a dynamic setting where investors' trust-based beliefs about the credibility of accounting information are not realized. © 2024 American Accounting Association. All rights reserved. | P68: institutional holdings; institutional investors; restatements; societal trust | R68: Article | S68: Final | U68: Scopus | V68: 2-s2.0-85187690921
A69: Glaeser S.A.; Landsman W.R. | B69: Glaeser, Stephen A. (57195741898); Landsman, Wayne R. (7003762923) | C69: 57195741898; 7003762923 | D69: Deterrent disclosure | E69: 2021 | F69: Accounting Review | G69: 96 | H69: 5 | J69: 291 | K69: 315 | L69: 68 | M69: 10.2308/TAR-2019-1050 | N69: https://www.scopus.com/inward/record.uri?eid=2-s2.0-85115174716&doi=10.2308%2FTAR-2019-1050&partnerID=40&md5=4ae8ac737e075f1e0686ef02e78b8f4a | O69: We examine how product market competition affects the disclosure of innovation. Theory posits that product market competition can cause firms to increase their disclosure of innovation to deter product market competitors. Consistent with this reasoning, we find that patent applicants in more competitive industries voluntarily accelerate their patent disclosures, which are credibly disclosed via the United States Patent and Trademark Office. Our inferences are robust to using changes in industry-level import tariffs as sources of plausibly exogenous variation in product market competition in difference-in-differences designs. Consistent with patent disclosure deterring product market competitors, we find that timelier patent disclosures are more strongly associated with declines in the similarity of competitors’ products than are less timely patent disclosures. In total, our results suggest that product market competition increases patent disclosure timeliness, which is consistent with firms using the disclosure of innovation to deter product market competition. © 2021 American Accounting Association. All rights reserved. | P69: Competition; Innovation; Patents; Voluntary disclosure | R69: Article | S69: Final | U69: Scopus | V69: 2-s2.0-85115174716
A70: Hepfer B.F. | B70: Hepfer, Bradford F. (57201461820) | C70: 57201461820 | D70: Are Book-Tax Differences Mispriced? | E70: 2023 | F70: Accounting Review | G70: 98 | H70: 3 | J70: 285 | K70: 306 | L70: 7 | M70: 10.2308/TAR-2020-0181 | N70: https://www.scopus.com/inward/record.uri?eid=2-s2.0-85162845097&doi=10.2308%2FTAR-2020-0181&partnerID=40&md5=e8e0b383651c92edb3c530e132802b06 | O70: I examine whether book-tax differences (BTDs) are mispriced. I predict that BTD mispricing is the operating cash flows-to-price (CFO/P) anomaly in disguise. Using both time-series asset pricing tests and cross-sectional returns tests, I provide consistent evidence that returns to trading on BTDs are explained by CFO/P. Rather than being an independent anomaly, the findings indicate that any evidence of BTD mispricing is subsumed by the broader CFO/P anomaly. These findings stand in contrast to many studies that infer BTDs possess unique information for future earnings reflected in stock prices with a delay. © 2023 American Accounting Association. All rights reserved. | P70: accrual anomaly; book-tax differences; growth anomaly; mispricing; operating cash flows-to-price | R70: Article | S70: Final | U70: Scopus | V70: 2-s2.0-85162845097
A71: Wang D.; Cooper S.M.; Chapman C.S.; Calace D. | B71: Wang, Di (59657869500); Cooper, Stuart M. (11139639000); Chapman, Christopher S. (35386152700); Calace, Donato (59978709000) | C71: 59657869500; 11139639000; 35386152700; 59978709000 | D71: Sustainability (Environmental, Social, and Governance) Reporting: Tracing Materiality’s Visionary and Relational Role over 25 Years through Boundary Objects and Boundary Work | E71: 2025 | F71: Accounting Review | G71: 100 | H71: 4 | J71: 417 | K71: 441 | L71: 5 | M71: 10.2308/TAR-2023-0675 | N71: https://www.scopus.com/inward/record.uri?eid=2-s2.0-105009920341&doi=10.2308%2FTAR-2023-0675&partnerID=40&md5=4d95495cfaff86c640982a318ca72f9b | O71: The concept of materiality has acquired great significance in sustainability reporting. Through the theoretical bricolage of boundary objects and boundary work and drawing upon 91 interviews, we trace materiality’s evolving role across four interconnected episodes. Our findings show that materiality begins as a multivisionary object that draws the attention of largely unconnected groups. As different actors become more aware of each other, materiality becomes a meeting point object, and then a discursive and bridge-like object for them to talk about their relationships. However, the subsequent escalation of competitive boundary work turns materiality into a divisive institutional object that inhibits cooperation. Moving beyond a view of materiality as a way to distinguish significant information within corporate reports, our analysis fleshes out the visionary and relational roles that materiality has performed in sustainability reporting for a broad range of field-level actors to see themselves and their relationships to others in new lights. © 2025 American Accounting Association. All rights reserved. | R71: Article | S71: Final | T71: All Open Access; Green Open Access | U71: Scopus | V71: 2-s2.0-105009920341
A72: Bushee B.J.; Huang Y.J. | B72: Bushee, Brian J. (6602721134); Huang, Ying Julie (42961591300) | C72: 6602721134; 42961591300 | D72: Do Analysts and Investors Efficiently Respond to Managerial Linguistic Complexity during Conference Calls? | E72: 2024 | F72: Accounting Review | G72: 99 | H72: 4 | J72: 143 | K72: 168 | L72: 14 | M72: 10.2308/TAR-2019-0358 | N72: https://www.scopus.com/inward/record.uri?eid=2-s2.0-85197683417&doi=10.2308%2FTAR-2019-0358&partnerID=40&md5=63fd5696e96f7ebcafe1c8deb2e4cdb0 | O72: This paper examines whether analysts and investors efficiently incorporate the informational signals from managerial linguistic complexity (e.g., Fog) into their forecasts and trading decisions. We predict that a manager’s Fog during a conference call provides a signal of their private information through their willingness to engage with analyst questions. We find that informative (obfuscatory) managerial Fog provides a positive (negative) signal of future earnings growth. We also find that analysts efficiently revise their forecasts to both positive and negative signals, whereas investors only correctly interpret obfuscation during the call; there is a delayed price reaction to informative Fog. However, when buy-side investors ask questions during a call, we find an efficient price reaction to informative Fog. Our findings highlight an important benefit of two-way interactive disclosures and underline the importance of active call participation for efficiently incorporating linguistic signals of managers’ private information. © 2024 American Accounting Association. All rights reserved. | P72: analyst forecasts; conference call; informative technical disclosure; linguistic complexity; market reaction; two-way engagement | R72: Article | S72: Final | T72: All Open Access; Bronze Open Access | U72: Scopus | V72: 2-s2.0-85197683417
A73: Proell C.A.; Zhou Y.; Nelson M.W. | B73: Proell, Chad A. (15063331900); Zhou, Yuepin (57205064444); Nelson, Mark W. (7403461219) | C73: 15063331900; 57205064444; 7403461219 | D73: It's Not Only What You Say . . . How Communication Style and Team Culture Affect Audit Issue Follow-Up and Auditor Performance Evaluations | E73: 2022 | F73: Accounting Review | G73: 97 | H73: 1 | J73: 373 | K73: 395 | L73: 21 | M73: 10.2308/TAR-2020-0198 | N73: https://www.scopus.com/inward/record.uri?eid=2-s2.0-85125648585&doi=10.2308%2FTAR-2020-0198&partnerID=40&md5=bd80ad266b3c670a2eb602378f255ada | O73: Auditors work in hierarchical teams in which effective upward communication is critical to audit quality. In these teams, subordinates choose both the content, as well as the style, of their communications. We report survey and experimental evidence of the importance of communication style in the context of audit team culture. Our first two studies provide evidence that audit staff perceive assertive upward communication as risky and prefer to communicate passively, especially in less autonomous team cultures. Our third study provides evidence that audit seniors consider more follow-up procedures and rate staff higher when staff communicate assertively, especially in more autonomous team cultures. Combined, these studies indicate a disconnect between audit seniors, who reward and follow up more on assertive communication, and their staff, who prefer passive communication. Our results suggest the potential for audit quality improvements by better alignment of supervisor-subordinate communicationstyle preferences, especially in more autonomous team cultures. © 2022 American Accounting Association. All rights reserved. | P73: audit teams; auditor performance assessment; communication style; information sharing; skeptical action; team culture; voice | R73: Article | S73: Final | U73: Scopus | V73: 2-s2.0-85125648585
A74: Bhojraj S.; Bloomfield R.J.; Jang Y.; Yehuda N. | B74: Bhojraj, Sanjeev (6701521606); Bloomfield, Robert J. (7005459727); Jang, Youngki (57223195144); Yehuda, Nir (31767780100) | C74: 6701521606; 7005459727; 57223195144; 31767780100 | D74: Cost structure, operating leverage, and CDS spreads | E74: 2021 | F74: Accounting Review | G74: 96 | H74: 5 | J74: 79 | K74: 105 | L74: 20 | M74: 10.2308/TAR-2018-0497 | N74: https://www.scopus.com/inward/record.uri?eid=2-s2.0-85105155911&doi=10.2308%2FTAR-2018-0497&partnerID=40&md5=7c9606914634a7aa1aff93fe75a6cdd2 | O74: We provide evidence that credit investors do not fully impound the implications of firms’ cost structure (or operating leverage) when pricing credit default swaps. Information about firms’ cost structure is not disclosed and needs to be estimated. Furthermore, the performance implications of firms’ cost structure depend on the expected macroeconomic conditions. We focus on the debt market because of the strong emphasis of this market on downside risk. To measure expected aggregate macroeconomic conditions, we employ the change in the anxious index (AI), which is the probability of a decline in real GDP provided by the SPF—the survey of professional forecasters. We find that the interaction between the firm’s cost structure and change in AI predicts one-quarter-ahead CDS spreads. Portfolio-level analysis confirms this result. © 2021 American Accounting Association. All rights reserved. | P74: Cost structure; Credit spreads; Macroeconomic forecast; Operating leverage | R74: Article | S74: Final | U74: Scopus | V74: 2-s2.0-85105155911
A75: Cao C.; Cheng C.S.A.; Xia C.; Xie J.; Zeng C.C. | B75: Cao, Chunfang (57158295400); Cheng, C.S. Agnes (59600278700); Xia, Changyuan (57191288995); Xie, Jing (57202960239); Zeng, Cheng Colin (57201921569) | C75: 57158295400; 59600278700; 57191288995; 57202960239; 57201921569 | D75: Corporate Tax Benefits from Hometown-Connected Politicians | E75: 2024 | F75: Accounting Review | G75: 99 | H75: 3 | J75: 59 | K75: 86 | L75: 8 | M75: 10.2308/TAR-2020-0162 | N75: https://www.scopus.com/inward/record.uri?eid=2-s2.0-85192340505&doi=10.2308%2FTAR-2020-0162&partnerID=40&md5=ef091d0d067ba7ea957bef9fd62c3c6a | O75: This study examines whether politicians exhibit hometown favoritism in assigning preferential corporate income tax rates. We find that firms with hometown connections to incumbent provincial leaders experience favorable tax treatment. This effect is more pronounced when those leaders have strong hometown preferences and weaker when they have a strong incentive to seek promotion, suggesting that social incentives are the primary drivers of the effects on corporate tax benefits of hometown favoritism by politicians. Moreover, this effect is intensified when members of senior management have personal connections with the provincial leader. The mechanism test reveals that the provincial governments tend to qualify connected firms for preferential tax policies under their jurisdictions. Overall, our results suggest that hometown favoritism by politicians promotes tax benefits for business entities. © 2024 American Accounting Association. All rights reserved. | P75: hometown favoritism; provincial leaders; social identity; tax benefits | R75: Article | S75: Final | U75: Scopus | V75: 2-s2.0-85192340505
A76: Kim Y.; Su L.; Wang Z.; Wu H. | B76: Kim, Yongtae (56683642200); Su, Lixin (14834435400); Wang, Zheng (44961631700); Wu, Haibin (56012584700) | C76: 56683642200; 14834435400; 44961631700; 56012584700 | D76: The Effect of Trade Secrets Law on Stock Price Synchronicity: Evidence from the Inevitable Disclosure Doctrine | E76: 2021 | F76: Accounting Review | G76: 96 | H76: 1 | J76: 325 | K76: 348 | L76: 122 | M76: 10.2308/TAR-2017-0425 | N76: https://www.scopus.com/inward/record.uri?eid=2-s2.0-85101279372&doi=10.2308%2FTAR-2017-0425&partnerID=40&md5=d9dd010fa6584f879292fa415d57afe8 | O76: We exploit the staggered recognition of the Inevitable Disclosure Doctrine (IDD) by U.S. state courts to examine the effect of trade secret protection on the amount of firm-specific information incorporated in stock prices, as reflected in stock price synchronicity. We find that after certain state courts recognize the IDD, firms headquartered in those states exhibit a significant increase in stock price synchronicity relative to firms in other states. We also find a significant decrease in the disclosure of proprietary information in the firms’ 10-K reports. These results suggest that IDD recognition increases the proprietary cost of disclosure and, in response, corporate managers withhold more information. In addition, we find that the increase in stock price synchronicity and the decrease in the disclosure of proprietary information lead to increases in the firm’s market share, cost of equity, and market-to-book ratio, suggesting that managers sacrifice capital market benefits for product market gains. © 2021 American Accounting Association. All rights reserved. | P76: Inevitable disclosure doctrine; Information environment; Proprietary cost of disclosure; Stock price synchronicity; Trade secrets law | R76: Article | S76: Final | T76: All Open Access; Green Open Access | U76: Scopus | V76: 2-s2.0-85101279372
A77: Giese V.; Heese J. | B77: Giese, Vincent (59422298700); Heese, Jonas (57192675919) | C77: 59422298700; 57192675919 | D77: The Effect of Financial Regulation on Nonfinancial Violations | E77: 2026 | F77: Accounting Review | G77: 101 | H77: 1 | J77: 347 | K77: 378 | L77: 0 | M77: 10.2308/TAR-2023-0676 | N77: https://www.scopus.com/inward/record.uri?eid=2-s2.0-105030228815&doi=10.2308%2FTAR-2023-0676&partnerID=40&md5=e12a0ae11a471ce854e35affe73b20db | O77: This paper examines the effect of financial regulation on nonfinancial violations. Using differences in compliance requirements with Sarbanes-Oxley Act of 2002 (SOX) Section 404, we find that adoption of Section 404 increased firms’ propensity for nonfinancial violations. This effect is stronger for firms with greater external scrutiny toward their financial reporting, greater challenges in monitoring their operations, and limited resources. These results, together with an examination of changes in audit fees, conference call transcripts, and 10-K disclosures, suggest that the effects primarily stem from a shift in attention and resources toward SOX 404. Further, the effects are concentrated in employee-related violations and persist for approximately two years. Overall, our results suggest that financial reporting regulation can result in unintended consequences harming stakeholders, such as employees. © 2026, American Accounting Association. All rights reserved. | P77: compliance; corporate misconduct; financial regulation; SOX 404 | R77: Article | S77: Final | T77: All Open Access; Bronze Open Access | U77: Scopus | V77: 2-s2.0-105030228815
A78: Meng X. | B78: Meng, Xiaojing (57208696138) | C78: 57208696138 | D78: Information, Incentives, and CEO Replacement | E78: 2024 | F78: Accounting Review | G78: 99 | H78: 2 | J78: 369 | K78: 393 | L78: 1 | M78: 10.2308/TAR-2019-0494 | N78: https://www.scopus.com/inward/record.uri?eid=2-s2.0-85187673690&doi=10.2308%2FTAR-2019-0494&partnerID=40&md5=43d75103391233256eaa8fc7cde0394b | O78: There are instances where CEO turnover occurs, even if the company has not made any significant strategy changes, and the new CEO possesses similar abilities as the predecessor. This paper aims to provide a rational explanation for this seemingly irrational phenomenon. One possible reason for this "aggressive" CEO turnover is the board's desire to reduce the information rents earned by the privately informed CEO. Specifically, the incumbent CEO has a temptation to "sandbag" the board about profitability prospects to secure more generous incentive pay for future implementation, and a (seemingly aggressive) replacement policy helps discourage this kind of gaming. That is, instead of "information-based entrenchment" as suggested by the literature (Laux 2008; Inderst and Mueller 2010), this paper shows a countervailing effect that the CEO's private information (combined with the later-stage moral hazard problem) may lead to her dismissal more often than the ex post efficient benchmark. © 2024 American Accounting Association. All rights reserved. | P78: CEO compensation; CEO replacement; information rent; sequential task; severance pay | R78: Article | S78: Final | U78: Scopus | V78: 2-s2.0-85187673690
A79: Duguay R. | B79: Duguay, Raphael (57224115905) | C79: 57224115905 | D79: The Effect of Financial Audits on Governance Practices: Evidence from the Nonprofit Sector | E79: 2024 | F79: Accounting Review | G79: 99 | H79: 6 | J79: 157 | K79: 189 | L79: 2 | M79: 10.2308/TAR-2022-0525 | N79: https://www.scopus.com/inward/record.uri?eid=2-s2.0-85208679034&doi=10.2308%2FTAR-2022-0525&partnerID=40&md5=b9e1e62a16707c7eb7b161163c535cfe | O79: I evaluate the effect of financial statement audits on the governance practices of nonprofit organizations. Using a regression discontinuity design that exploits revenue-based exemption thresholds, I find that financial audits cause organizations to implement governance mechanisms, such as conflict of interest policies, whistleblower policies, and formal approval of the CEO's compensation by a committee. Consistent with these governance practices curtailing managers' private benefits, I document reductions in nepotism and CEO-to-employee pay ratio. The results are more pronounced for organizations (1) whose audit is overseen by an audit committee, (2) that already have an independent board, and (3) that face high charity-level demand for oversight. Collectively, these findings shed light on how financial audits shape the governance practices of small, less sophisticated organizations like nonprofits in ways that go beyond financial statements' direct use in decision-making and contracting. © 2024 American Accounting Association. All rights reserved. | P79: auditing; governance; nonprofit organizations; real effects | R79: Article | S79: Final | U79: Scopus | V79: 2-s2.0-85208679034
A80: Brown A.B.; Byard D.; Darrough M.; Suh J. | B80: Brown, Anna Bergman (21233569600); Byard, Donal (22984377800); Darrough, Masako (6602529908); Suh, Jangwon (57194498962) | C80: 21233569600; 22984377800; 6602529908; 57194498962 | D80: The Impact of M&A Delistings on the Information Environment of Industry Peer Firms | E80: 2024 | F80: Accounting Review | G80: 99 | H80: 2 | J80: 85 | K80: 112 | L80: 4 | M80: 10.2308/TAR-2021-0442 | N80: https://www.scopus.com/inward/record.uri?eid=2-s2.0-85187674772&doi=10.2308%2FTAR-2021-0442&partnerID=40&md5=be43fe56347b68f80c2161da0bf37939 | O80: This study documents that M&A delistings are associated with a deterioration in the quality of analysts' information environment for industry peer firms, measured by an increase in analysts' absolute forecast errors and dispersion. This effect persists for six quarters and is larger when the delisting target firm contributes relatively more to the industry information environment. Further, we find that, among analysts forecasting earnings for an industry peer firm, those who also followed the delisted target firm in the pre-M&A period experience a larger increase in their absolute forecast errors. A comparison based on public versus private target firms also suggests that the loss of target firms' public disclosures plays a role in the deterioration in the quality of analysts' information environment. In additional analyses, we find evidence consistent with this effect resulting from a deterioration in analysts' ability to exploit across-firm information complementarities. © 2024 American Accounting Association. All rights reserved. | P80: analyst information environment; industry peer firms; M&A delisting; negative information externalities; spillovers | R80: Article | S80: Final | U80: Scopus | V80: 2-s2.0-85187674772
A81: McDonough R.P.; McLelland A.J.; Warren J.D. | B81: McDonough, Ryan P. (56672589400); McLelland, Andrew J. (6701345882); Warren, J. Donald (58714468900) | C81: 56672589400; 6701345882; 58714468900 | D81: A Century of Progress: U.S. Government Accountability Office Procedures, Reports, and Performance Measures | E81: 2023 | F81: Accounting Review | G81: 35 | H81: 3 | L81: 0 | M81: 10.2308/HORIZONS-2022-016 | N81: https://www.scopus.com/inward/record.uri?eid=2-s2.0-85173728965&doi=10.2308%2FHORIZONS-2022-016&partnerID=40&md5=bf081118e0f2d31921845352dac11711 | O81: In 2021, the U.S. Government Accountability Office (GAO) celebrated its 100th anniversary, and its mission has never been more critical. This study documents the 100-year history of GAO, examining how Congressional law changes and leadership influences of the Comptroller General of the United States have shaped GAO’s role, services, and products. GAO has transformed from focusing on providing oversight through its audits of federal government expenditures during its early years (e.g., to assess legality) to emerging as a leader in providing insights to Congress through program evaluation audits and, more recently, to providing Congress the foresight necessary to confront the challenges and opportunities that lie ahead. © 2023 American Accounting Association. All rights reserved. | P81: accountability; GAO; General Accounting Office; Government Accountability Office; performance and accountability reports; public sector auditing; reports; testimonies | R81: Article | S81: Final | T81: All Open Access; Bronze Open Access | U81: Scopus | V81: 2-s2.0-85173728965
A82: Huang S.; Ng J.; Ranasinghe T.; Zhang M. | B82: Huang, Sterling (57103970700); Ng, Jeffrey (37091445400); Ranasinghe, Tharindra (55791711800); Zhang, Mingyue (57222068482) | C82: 57103970700; 37091445400; 55791711800; 57222068482 | D82: Do Innovative Firms Communicate More? Evidence from the Relation between Patenting and Management Guidance | E82: 2021 | F82: Accounting Review | G82: 96 | H82: 1 | J82: 273 | K82: 297 | L82: 50 | M82: 10.2308/TAR-2017-0082 | N82: https://www.scopus.com/inward/record.uri?eid=2-s2.0-85101280235&doi=10.2308%2FTAR-2017-0082&partnerID=40&md5=9aebcab2abc54fc4a86db3fa280c3daf | O82: Successful innovations could induce more disclosure if the information asymmetry between the firm and its investors about post-innovation outcomes leads investors to demand more information. However, such innovations also likely entail greater proprietary cost concerns, which deter disclosure. This paper uses patent grants to examine the effect of innovation success on management guidance behavior. We find that more management guidance follows patent grants, suggesting that despite disclosure cost concerns, firms with successful innovations do respond to information demand. This association is stronger after enactment of Regulation Fair Disclosure and for firms with greater institutional investor ownership, further highlighting the role of information demand. The association is weaker for firms with more competition, consistent with proprietary cost concerns having a moderating impact. Overall, our findings suggest that innovation creates demand for more voluntary disclosure, and firms’ disclosure decisions following innovation outcomes vary in ways that disclosure theory and economic intuition predict. © 2021 American Accounting Association. All rights reserved. | P82: Innovation; Management forecasts; Patents; Voluntary disclosure | R82: Article | S82: Final | T82: All Open Access; Green Open Access | U82: Scopus | V82: 2-s2.0-85101280235
A83: Easton P.D.; Kapons M.M.; Monahan S.J.; Schutt H.H.; Weisbrod E.H. | B83: Easton, Peter D. (7004696872); Kapons, Martin M. (57226170630); Monahan, Steven J. (6701503900); Schutt, Harm H. (57190582413); Weisbrod, Eric H. (26424149200) | C83: 7004696872; 57226170630; 6701503900; 57190582413; 26424149200 | D83: Forecasting Earnings Using k-Nearest Neighbors | E83: 2024 | F83: Accounting Review | G83: 99 | H83: 3 | J83: 115 | K83: 140 | L83: 9 | M83: 10.2308/TAR-2021-0478 | N83: https://www.scopus.com/inward/record.uri?eid=2-s2.0-85182101135&doi=10.2308%2FTAR-2021-0478&partnerID=40&md5=4edaed8a0578284434ec4158ae170d80 | O83: We use a simple k-nearest neighbors algorithm (hereafter, k-NN*) to forecast earnings. k-NN* forecasts of one-, two-, and three-year-ahead earnings are more accurate than those generated by popular extant forecasting approaches. k-NN* forecasts of two- and three-year (one-year)-ahead EPS and aggregate three-year EPS are more (less) accurate than those generated by analysts. The association between the unexpected earnings implied by k-NN* and the contemporaneous market-adjusted return (i.e., the earnings association coefficient (EAC)) is positive and exceeds the EAC on unexpected earnings implied by alternate approaches. A trading strategy that is long (short) firms for which k-NN* predicts positive (negative) earnings growth earns positive risk-adjusted returns that exceed those earned by similar trading strategies that are based on alternate forecasts. The k-NN* algorithm generates an empirically reliable ex ante indicator of forecast accuracy that identifies situations when the k-NN* EAC is larger and the k-NN* trading strategy is more profitable. © 2024 American Accounting Association. All rights reserved. | P83: earnings; forecasting; machine learning; nearest neighbors | R83: Article | S83: Final | U83: Scopus | V83: 2-s2.0-85182101135
A84: He J.; Li K.; Li N.; Zhang W. | B84: He, Jiapeng (58937453500); Li, Kevin (57226143723); Li, Ningzhong (56257074000); Zhang, Weining (55261814700) | C84: 58937453500; 57226143723; 56257074000; 55261814700 | D84: Proprietary Information Cost of Contracting with the Government | E84: 2024 | F84: Accounting Review | G84: 99 | H84: 2 | J84: 195 | K84: 227 | L84: 5 | M84: 10.2308/TAR-2022-0351 | N84: https://www.scopus.com/inward/record.uri?eid=2-s2.0-85187649484&doi=10.2308%2FTAR-2022-0351&partnerID=40&md5=9bfd459a7b868afd111dd92f6d3706dd | O84: We argue that contracting with the federal government involves significant proprietary information cost due to regulations requiring contractors to provide proprietary information, which may become available to outsiders via Freedom of Information Act (FOIA) requests. We provide evidence by showing that firms become more willing to bid for government contracts after a recent Supreme Court ruling on FOIA (Food Marketing Institute v. Argus Leader Media) that improved information protection for contractors and that this effect strengthens when the contracts entail higher proprietary information cost for contractors. © 2024 American Accounting Association. All rights reserved. | P84: Food Marketing Institute v. Argus Leader Media; Freedom of Information Act; government contractors; proprietary information cost | R84: Article | S84: Final | U84: Scopus | V84: 2-s2.0-85187649484
A85: Roh Y. | B85: Roh, Yongoh (57102812600) | C85: 57102812600 | D85: Internal Accounting Hiring and Operational Efficiency: Evidence from the Implementation of ASC 842 | E85: 2025 | F85: Accounting Review | G85: 100 | H85: 5 | J85: 317 | K85: 344 | L85: 0 | M85: 10.2308/TAR-2023-0253 | N85: https://www.scopus.com/inward/record.uri?eid=2-s2.0-105014733673&doi=10.2308%2FTAR-2023-0253&partnerID=40&md5=36fee7fafaad813c983458e80f30329f | O85: ASC 842 requires firms to collect and analyze lease contracts for accounting classification, measurement, and recognition purposes. Leveraging the implementation of ASC 842, I examine firms’ internal accounting hiring and its impact on the efficiency of lease management. I find that the standard prompts lease-intensive firms to significantly increase their internal accounting hiring, which enhances lease-related financial reporting quality. Moreover, firms that increased accounting hiring achieve greater efficiency in managing leases than those that implemented the standard without such hiring. This efficiency gain is incremental to improvements from concurrent information system upgrades and is more pronounced in firms with greater cost-saving opportunities and those that hire more experienced accountants. These results highlight that the benefits of internal accounting hiring extend beyond financial reporting, improving firms’ operational decisions. © 2025 American Accounting Association. All rights reserved. | P85: accountants; accounting employees; ASC 842; lease standard; operational efficiency; standard implementation | R85: Article | S85: Final | T85: All Open Access; Bronze Open Access | U85: Scopus | V85: 2-s2.0-105014733673
A86: Chang Y.-C.; Tseng K.; Yu T.-W. | B86: Chang, Yen-Cheng (56544806500); Tseng, Kevin (57201336531); Yu, Tzu-Wen (59318915000) | C86: 56544806500; 57201336531; 59318915000 | D86: Access to Financial Disclosure and Knowledge Spillover | E86: 2024 | F86: Accounting Review | G86: 99 | H86: 5 | J86: 147 | K86: 170 | L86: 6 | M86: 10.2308/TAR-2023-0406 | N86: https://www.scopus.com/inward/record.uri?eid=2-s2.0-85203417693&doi=10.2308%2FTAR-2023-0406&partnerID=40&md5=5c41a828b386e7fdc2ed7b10284bf235 | O86: Access to firms’ innovation outputs determines the extent of knowledge spillover that poses risk to innovation appropriability. We provide plausibly causal evidence that processing costs of financial disclosures, which inform users of the economic value of innovation, play a key role in firms’ management of knowledge spillover. We exploit an exogenous, randomly assigned, and staggered policy shock by the SEC that reduces processing costs of mandatory financial disclosures. In response, firms reduce patenting rates, with the effect concentrated among firms in more competitive industries and with lower costs of capital. Firms also reduce their patent disclosure quality. Our results suggest firms rely more on trade secrecy as their innovation property protection mechanism. Lower processing costs of financial disclosures affect neither innovation inputs nor voluntary disclosure practices. Our results show that firms strategically manage access to their innovation outputs through financial disclosures, patent disclosures, and trade secrecy to curb knowledge spillover. © 2024 American Accounting Association. All rights reserved. | P86: disclosure; EDGAR; innovation; knowledge spillover; patents; trade secrets | R86: Article | S86: Final | U86: Scopus | V86: 2-s2.0-85203417693
A87: Li Z.; Ye K.; Zeng C.; Zhang B. | B87: Li, Zhe (57218388462); Ye, Kangtao (35590908500); Zeng, Cheng (57201921569); Zhang, Bo (59278009000) | C87: 57218388462; 35590908500; 57201921569; 59278009000 | D87: Ending at the Wrong Time: The Financial Reporting Consequences of a Uniform Fiscal Year-End | E87: 2023 | F87: Accounting Review | G87: 98 | H87: 3 | J87: 367 | K87: 396 | L87: 11 | M87: 10.2308/TAR-2018-0461 | N87: https://www.scopus.com/inward/record.uri?eid=2-s2.0-85162224981&doi=10.2308%2FTAR-2018-0461&partnerID=40&md5=a114dd2cebaac23c89ba8c17afa300a4 | O87: There is an ongoing debate over uniformity versus flexibility in accounting regulation. This study examines the financial reporting consequences of a rigid accounting rule in China under which the fiscal year-end is uniform for all companies. Using extensive interviews together with large-sample archival analyses, we find that “mismatched” firms—those whose mandated financial reporting cycles are not aligned with their business cycles—exhibit higher levels of absolute abnormal accruals than their nonmismatched counterparts. Further analyses suggest that the negative association between mismatching and financial reporting quality is mainly driven by unintentional estimation errors rather than intentional earnings manipulation. © 2023 American Accounting Association. All rights reserved. | P87: accounting period; business cycle; financial reporting quality; uniformity | R87: Article | S87: Final | U87: Scopus | V87: 2-s2.0-85162224981
A88: Bartov E.; Marra A.; Momenté F. | B88: Bartov, Eli (7004211924); Marra, Antonio (36696667700); Momenté, Francesco (22937978600) | C88: 7004211924; 36696667700; 22937978600 | D88: Corporate social responsibility and the market reaction to negative events: Evidence from inadvertent and fraudulent restatement announcements | E88: 2021 | F88: Accounting Review | G88: 96 | H88: 2 | J88: 81 | K88: 106 | L88: 86 | M88: 10.2308/TAR-2018-0281 | N88: https://www.scopus.com/inward/record.uri?eid=2-s2.0-85104815805&doi=10.2308%2FTAR-2018-0281&partnerID=40&md5=3642ef9d65534a85c7d93243b9645ee8 | O88: We advance a theory asserting that CSR performance may exacerbate, not necessarily moderate, a company's negative stock price response to negative events. In testing this theory, we hypothesize and find that CSR performance alleviates (magnifies) the immediate negative stock price response to inadvertent (fraudulent) restatement announcements, and that these findings are robust to specifications that consider alternative CSR measures and a multitude of control variables shown by prior research to have explanatory power for the cross-sectional variation in stock returns. Overall, using restatement announcements as a channel through which CSR performance may affect company value, we show, in contrast to prior research, that depending on management conduct leading to the restatement, a company's CSR performance may destroy, not necessarily enhance, firm value. Our findings may, thus, inform researchers, market participants, and regulators. © 2021 American Accounting Association. All rights reserved. | P88: Accounting fraud; Accounting restatements; Corporate social responsibility; Inadvertent accounting errors; Negative events | R88: Review | S88: Final | U88: Scopus | V88: 2-s2.0-85104815805
A89: Nieken P.; Ressi A. | B89: Nieken, Petra (26635716200); Ressi, Anna (57090737700) | C89: 26635716200; 57090737700 | D89: Where Do I Belong? Prospective Relative Performance Information under High- and Low-Performing Reference Groups | E89: 2025 | F89: Accounting Review | G89: 100 | H89: 3 | J89: 421 | K89: 444 | L89: 1 | M89: 10.2308/TAR-2023-0275 | N89: https://www.scopus.com/inward/record.uri?eid=2-s2.0-105009516147&doi=10.2308%2FTAR-2023-0275&partnerID=40&md5=840598eb56ac45fd7cc0442c3de1e1fb | O89: We present two experiments on the behavioral effects of prospective relative performance information (RPI) when facing multiple reference groups that differ in their implicit performance standard. In Study 1, employees are exogenously assigned to either a high- or low-standard reference group. Our results suggest that employees generally seek to enhance their sense of belonging by conforming to the standard. However, RPI boosts the performance of high-performers assigned to the low-standard group, whereas low-performers assigned to the high-standard group show decreased performance. This indicates that RPI may reinforce a sense of not belonging. In Study 2, where employees self-select their reference group, our results suggest that they generally sort themselves according to their sense of belonging. Anticipating RPI, however, can induce employees to select the high-standard group as a self-set target, spurring motivation. Overall, our studies shed more light on the costs and benefits of RPI and self-selection options. © 2025 American Accounting Association. All rights reserved. | P89: performance standards; reference groups; relative performance information; self-selection | R89: Article | S89: Final | T89: All Open Access; Bronze Open Access | U89: Scopus | V89: 2-s2.0-105009516147
A90: Sul E.S. | B90: Sul, Edward S. (56497002600) | C90: 56497002600 | D90: Takeover Threats, Job Security Concerns, and Earnings Management | E90: 2024 | F90: Accounting Review | G90: 99 | H90: 3 | J90: 451 | K90: 477 | L90: 7 | M90: 10.2308/TAR-2020-0144 | N90: https://www.scopus.com/inward/record.uri?eid=2-s2.0-85192325366&doi=10.2308%2FTAR-2020-0144&partnerID=40&md5=ed12bf488818c705661bcf52fed6567d | O90: Using the staggered adoption of takeover laws, this study examines implications of takeover threats on earnings management around the world. I find that the enactment of takeover legislation leads to increased earnings management (abnormally high accruals, target beating, and poor accruals quality). Results are driven by underperforming managers with higher turnover risk in countries with high increases in turnover sensitivity to performance, indicating job security concerns as the channel through which takeover laws increase earnings management. Furthermore, results are strongest in countries with weak investor protection, where existing governance mechanisms are weaker and earnings management is more prevalent. Moreover, regulation provisions that most directly increase takeover threats experience greater earnings management responses. Additionally, I show that accounting restatements and fraud scandals become more frequent following takeover legislation. Overall, I provide evidence that takeover reforms, although enhancing discipline of underperforming managers, inadvertently incentivize accounting manipulation due to heightened job security concerns. © 2024 American Accounting Association. All rights reserved. | P90: CEO job security; corporate governance; earnings management; international accounting; investor protection; takeover legislation; takeover threats | R90: Article | S90: Final | T90: All Open Access; Bronze Open Access | U90: Scopus | V90: 2-s2.0-85192325366
A91: Li H.; Li S. | B91: Li, Haidan (36242024900); Li, Siqi (36009025200) | C91: 36242024900; 36009025200 | D91: The Changing Role of Accrual Accounting: International Evidence | E91: 2023 | F91: Accounting Review | G91: 35 | H91: 3 | L91: 0 | M91: 10.2308/JIAR-2022-019 | N91: https://www.scopus.com/inward/record.uri?eid=2-s2.0-85173770124&doi=10.2308%2FJIAR-2022-019&partnerID=40&md5=22d03427591d35282fcd69a19feabc13 | O91: Under the accrual accounting model, the timing role of accruals leads to a negative correlation between accruals and cash flows. Our study investigates the time-series trend of the timing role of accruals and finds a temporal decline in the magnitude of the correlation between accruals and cash flows in our sample of 51 countries over 1991–2019. This decline is primarily caused by increases in loss firms and operation volatility. Several accounting and economic factors, such as the use of accrual accounting, discretionary accruals, matching between revenues and expenses, IFRS adoption, and accounting connectedness, are positively associated with the strength of the accrual-cash flow relation and therefore decelerate the decline of the accrual timing role. Additional analysis suggests that the decline in accrual timing over time is present regardless of a country’s economic growth, legal tradition or institutions, and the extent of the use of accrual accounting. © 2023 American Accounting Association. All rights reserved. | P91: accrual accounting; accrual-cash flow relation; international accounting | R91: Article | S91: Final | U91: Scopus | V91: 2-s2.0-85173770124
A92: Jiang X.; Xin B. | B92: Jiang, Xu (57201843057); Xin, Baohua (35270281600) | C92: 57201843057; 35270281600 | D92: Financial Reporting Discretion, Managerial Myopia, and Investment Efficiency | E92: 2022 | F92: Accounting Review | G92: 97 | H92: 1 | J92: 291 | K92: 316 | L92: 28 | M92: 10.2308/TAR-2017-0342 | N92: https://www.scopus.com/inward/record.uri?eid=2-s2.0-85127587434&doi=10.2308%2FTAR-2017-0342&partnerID=40&md5=ab6ca2ac1b9916defc3d5ff66ab86a3c | O92: We explicitly model financial reporting discretion and earnings management in an investment setting where managers have incentives to behave myopically. We show that when managers are sufficiently, but not excessively, myopic, granting them some discretion over the mandatory financial reports can lead to better investment decisions. This finding contrasts with the conventional argument that financial reporting discretion facilitates earnings management and exacerbates managerial myopia, leading to inefficient investments. Costly earnings management, while offering managers some ex post protection against bad luck by decreasing the incidence of low financial reports, reduces the expected net benefit of high financial reports ex ante. Consequently, managers with negative private information find it too costly to mimic those with positive private information, facilitating separation of managers through efficient investment. Thus, curbing managerial myopia by removing or overly restricting earnings management may have the unintended consequence of impairing investment efficiency. © 2022 American Accounting Association. All rights reserved. | P92: earnings management; financial disclosure; managerial myopia; real effects; reporting discretion | R92: Article | S92: Final | U92: Scopus | V92: 2-s2.0-85127587434
A93: Göx R.F.; Michaeli B. | B93: Göx, Robert F. (22984505200); Michaeli, Beatrice (57195726326) | C93: 22984505200; 57195726326 | D93: Private Pre-Decision Information and the Pay-Performance Relation | E93: 2023 | F93: Accounting Review | G93: 98 | H93: 2 | J93: 177 | K93: 199 | L93: 4 | M93: 10.2308/TAR-2019-0665 | N93: https://www.scopus.com/inward/record.uri?eid=2-s2.0-85175486874&doi=10.2308%2FTAR-2019-0665&partnerID=40&md5=18ea0336f8c1793632354d96b6e5c0ff | O93: We study how the precision of managers' private post-contract pre-decision information affects the pay-performance relation. Endogenizing the information environment, we find that firms may optimally tie executive pay closer to firm performance as agency problems become more pronounced. Specifically, varying parameters measuring the severity of the agency problem, we identify parameter regions where firms with more pronounced agency problems optimally combine uninformative signals with a higher incentive rate than firms with less pronounced agency problems that optimally choose a perfect signal. We find this relation for various measures of the agency conflict such as the incongruency of the performance measure, its susceptibility to manipulation, or the agent's degree of risk aversion. Because the pay-performance sensitivity is frequently used for measuring the efficiency of real-world compensation arrangements, our results provide relevant insights for empirical research studying the determinants of the relation between executive pay and firm performance. © 2023 American Accounting Association. All rights reserved. | P93: incentive contracting; information design; pay-performance relation; pre-decision information | R93: Article | S93: Final | U93: Scopus | V93: 2-s2.0-85175486874
A94: Bauckloh T.; Hardeck I.; Inger K.K.; Wittenstein P.; Zwergel B. | B94: Bauckloh, Tobias (57201802258); Hardeck, Inga (55808593100); Inger, Kerry K. (56118166300); Wittenstein, Patrick (56897134800); Zwergel, Bernhard (26644632100) | C94: 57201802258; 55808593100; 56118166300; 56897134800; 26644632100 | D94: Spillover effects of tax avoidance on peers' firm value | E94: 2021 | F94: Accounting Review | G94: 96 | H94: 4 | J94: 51 | K94: 79 | L94: 29 | M94: 10.2308/TAR-2018-0441 | N94: https://www.scopus.com/inward/record.uri?eid=2-s2.0-85111531315&doi=10.2308%2FTAR-2018-0441&partnerID=40&md5=096866e98c5e4f535cdaa61cd8ab9cfc | O94: This research examines spillover effects of tax avoidance on peers' firm value using the setting of the European Commission's state aid investigations of private letter rulings. We assume that news about a firm's tax avoidance strategies also reveals information about peers' tax avoidance because investors expect similar firms to use similar strategies. Based on an event study design, we show that news about potential costs of tax avoidance of targeted U.S. multinational firms leads to negative stock price reactions among their peers. Moreover, peers' investors adjust their evaluations upward for news in favor of the targeted firms. Consistent with the level of tax avoidance being indicative of having similar strategies, spillover effects are stronger for firms with the highest levels of tax avoidance when examining a broad set of peers. Our findings suggest the need for a more comprehensive understanding of the costs and benefits of tax avoidance. © 2021 American Accounting Association. All rights reserved. | P94: EC state aid; Peer effects; Spillover effects; Tax avoidance | R94: Article | S94: Final | U94: Scopus | V94: 2-s2.0-85111531315
A95: Cainas J.M. | B95: Cainas, Jennifer M. (57224922873) | C95: 57224922873 | D95: The Road Less Traveled: A Nontraditional Path to Teaching and Scholarship | E95: 2026 | F95: Accounting Review | G95: 101 | H95: 1 | J95: 503 | K95: 508 | L95: 0 | M95: 10.2308/TAR-2025-0553 | N95: https://www.scopus.com/inward/record.uri?eid=2-s2.0-105030262230&doi=10.2308%2FTAR-2025-0553&partnerID=40&md5=77249f3c34ab1725d906310194f15103 | O95: This paper discusses my experiences as a nontenure track faculty member who now serves as an Associate Dean. It is based on my Presidential Scholar Lecture at the 2024 American Accounting Association Annual Meeting. In 2012, the Pathways Commission outlined the need and a path for more practitioners to join academia (Behn et al. 2012), and my academic career advanced partly due to that initiative. Earning a Doctor of Business Administration (D.B.A.) degree from University of Florida allowed me to support my school as a scholarly academic and pursue research that enhances my teaching and provided me with a path to administration as a nontenure track faculty member. © 2026, American Accounting Association. All rights reserved. | P95: administration; career; Doctor of Business Administration; pipeline; teaching | R95: Article | S95: Final | T95: All Open Access; Bronze Open Access | U95: Scopus | V95: 2-s2.0-105030262230
A96: Yang H.-C. | B96: Yang, Hsiang-Chieh (57286571500) | C96: 57286571500 | D96: How Does Loan Loss Accounting Influence Bank Lending? Evidence from the Current Expected Credit Loss (CECL) Model | E96: 2025 | F96: Accounting Review | G96: 100 | H96: 1 | J96: 465 | K96: 490 | L96: 4 | M96: 10.2308/TAR-2022-0511 | N96: https://www.scopus.com/inward/record.uri?eid=2-s2.0-85214925958&doi=10.2308%2FTAR-2022-0511&partnerID=40&md5=0d038cf6d24fdb32923d86424c9c66dc | O96: I explore the real effects of an update in loan loss accounting, the current expected credit loss (CECL) model. Although CECL’s predecessor only required banks to recognize losses after an event that made a loan uncollectible, CECL requires banks to recognize expected lifetime credit losses when originating loans. CECL’s earlier recognition of loan losses increases the cost of reserving regulatory capital for loans, decreasing banks’ willingness to lend. Empirically, I find that, following CECL’s approval, capital-constrained banks reduce their growth of total loans and residential loans. I also find that, for the residential loans banks continue to make, they choose to sell more shortly after origination, increasing the size of their originate-to-distribute (OTD) business. The increase in OTD mortgages is more pronounced for public banks, implying that their need to adopt CECL earlier than private banks outweighs the fact that they have better access to additional capital. © 2025 American Accounting Association. All rights reserved. | P96: bank lending; current expected credit losses (CECL); loan loss provisioning; originate-to-distribute (OTD) lending; real effects | R96: Article | S96: Final | U96: Scopus | V96: 2-s2.0-85214925958
A97: Chen C.-W.; Correia M.; Urcan O. | B97: Chen, Ciao-Wei (57200568247); Correia, Maria (38761122600); Urcan, Oktay (38362586900) | C97: 57200568247; 38761122600; 38362586900 | D97: Accounting for Leases and Corporate Investment | E97: 2023 | F97: Accounting Review | G97: 98 | H97: 3 | J97: 109 | K97: 133 | L97: 12 | M97: 10.2308/TAR-2018-0406 | N97: https://www.scopus.com/inward/record.uri?eid=2-s2.0-85162738939&doi=10.2308%2FTAR-2018-0406&partnerID=40&md5=adafaa53791b7b10a4c6f63d3c5d6a67 | O97: We examine the real effects of lease-capitalization rules (i.e., standards that require firms to capitalize finance leases) on corporate investment. We show that the introduction of these rules leads to a decrease in investment, which is more pronounced for firms with high reliance on leases. We posit and find that lease capitalization affects investment via a learning channel and a contracting channel. Regarding the first channel, we argue that managers identify areas of overinvestment and activities that should be discontinued or downsized because of the information they collect and analyze to comply with lease-capitalization rules. Accordingly, we find that the effect of lease capitalization is stronger when learning opportunities are higher. Regarding the second channel, we argue that lease capitalization affects investment via its effect on contracts. Accordingly, we document an increase in the likelihood of covenant breaches and a stronger decline in investment for financially constrained firms. © 2023 American Accounting Association. All rights reserved. | P97: disclosure; investment; lease; real effects | R97: Article | S97: Final | T97: All Open Access; Green Open Access | U97: Scopus | V97: 2-s2.0-85162738939
A98: Guest N.M.; Kothari S.P.; Pozen R.C. | B98: Guest, Nicholas M. (57188734112); Kothari, S.P. (7102665346); Pozen, Robert C. (6603483891) | C98: 57188734112; 7102665346; 6603483891 | D98: Why Do Large Positive Non-GAAP Earnings Adjustments Predict Abnormally High CEO Pay? | E98: 2022 | F98: Accounting Review | G98: 97 | H98: 6 | J98: 297 | K98: 326 | L98: 17 | M98: 10.2308/TAR-2019-0003 | N98: https://www.scopus.com/inward/record.uri?eid=2-s2.0-85143075843&doi=10.2308%2FTAR-2019-0003&partnerID=40&md5=e633ef323ace805118b001839c9c4be0 | O98: CEOs of S&P 500 firms that report high non-GAAP earnings relative to GAAP earnings receive substantial unexplained pay. Crucially, this result remains even after controlling for the level of non-GAAP and GAAP earnings. These firms are relatively poor performers (i.e., low GAAP earnings and stock returns) and have less powerful CEOs, consistent with non-GAAP earnings being used as justification when high executive pay is more likely to cause outrage. Additionally, despite the lower GAAP and return performance, these firms are more likely to beat the earnings targets specified in their compensation plans, which likely increases investors’ perceptions of core operating earnings and reduces outrage. Indeed, these firms face less dissent from shareholders and proxy advisors, and no additional media scrutiny. Our evidence suggests that the fraction of CEO pay that seems attributable to opportunistic non-GAAP reporting, while limited, is economically meaningful. © 2022 American Accounting Association. All rights reserved. | P98: CEO pay; corporate governance; non-GAAP earnings; performance evaluation | R98: Article | S98: Final | U98: Scopus | V98: 2-s2.0-85143075843
A99: Nakhmurina A. | B99: Nakhmurina, Anya (57225956507) | C99: 57225956507 | D99: Does Fiscal Monitoring Make Better Governments? Evidence from U.S. Municipalities | E99: 2024 | F99: Accounting Review | G99: 99 | H99: 4 | J99: 395 | K99: 425 | L99: 10 | M99: 10.2308/TAR-2020-0251 | N99: https://www.scopus.com/inward/record.uri?eid=2-s2.0-85197673750&doi=10.2308%2FTAR-2020-0251&partnerID=40&md5=f3d21e5043d327ab5912cb7317d2bf92 | O99: This paper examines the effect of state-level monitoring on municipal governance, focusing on outcomes in financial reporting quality, local corruption, political entrenchment, and municipal financial soundness. I exploit the staggered adoption of fiscal monitoring policies that entail a regular review of municipal financial reports for signs of fiscal distress. I find that introducing these monitoring policies is associated with an increase in the proxies for reporting quality, a decrease in the number of corruption convictions, and a reduction in re-election likelihood for incumbent politicians. Consistent with the purpose of the policies, my evidence shows that fiscal health ratios of municipalities improve after initiating state monitoring. Collectively, my results are consistent with state fiscal monitoring improving several important aspects of municipal governance. © 2024 American Accounting Association. All rights reserved. | P99: financial reports; governance; local governments; monitoring; stewardship | R99: Article | S99: Final | T99: All Open Access; Bronze Open Access | U99: Scopus | V99: 2-s2.0-85197673750
A100: Arya A.; Ramanan R.N.V. | B100: Arya, Anil (7006079514); Ramanan, Ram N.V. (55964743400) | C100: 7006079514; 55964743400 | D100: Disclosure to Regulate Learning in Product Markets from the Stock Market | E100: 2022 | F100: Accounting Review | G100: 97 | H100: 3 | J100: 1 | K100: 25 | L100: 5 | M100: 10.2308/TAR-2020-0033 | N100: https://www.scopus.com/inward/record.uri?eid=2-s2.0-85140056342&doi=10.2308%2FTAR-2020-0033&partnerID=40&md5=c6081a7c96f814dbdf47336a1281d57b | O100: A firm’s stock price may reveal information to a variety of participants, including its strategic partners and competitive rivals. This paper establishes that when a firm discloses cost information it can confound decision-relevant demand information embedded in the stock price that observers can otherwise extract. With stock price valuing firm profit (not cost and revenue separately), a disconnect is introduced between the firm’s actions and its intent—it discloses more (less) on one dimension when its intent is to conceal (reveal) on another. Moreover, the firm’s intent can be to either reveal or conceal information depending on what gives its partner the best competitive edge over its rival. Consequently, a firm’s disclosure is made strategically, incorporating both valuation and competitive effects. Interestingly, the firm’s disclosure strategy is designed in close concert with its production decision, i.e., the firm’s optimal accounting and real decisions interact with each other for maximum impact. © 2022 American Accounting Association. All rights reserved. | P100: competition; financial experts; stock market feedback; voluntary disclosure | R100: Article | S100: Final | U100: Scopus | V100: 2-s2.0-85140056342
...

Sheet Journals
A1: Journal | B1: 2021 | C1: =+B1+1 -> 2022 | D1: =+C1+1 -> 2023 | E1: =+D1+1 -> 2024 | F1: =+E1+1 -> 2025 | G1: =+F1+1 -> 2026 | H1: Total
A2: European Accounting Review | B2: =+COUNTIFS(Results!$F:$F,Journals!$A2,Results!$E:$E,Journals!B$1) -> 37 | C2: =+COUNTIFS(Results!$F:$F,Journals!$A2,Results!$E:$E,Journals!C$1) -> 42 | D2: =+COUNTIFS(Results!$F:$F,Journals!$A2,Results!$E:$E,Journals!D$1) -> 44 | E2: =+COUNTIFS(Results!$F:$F,Journals!$A2,Results!$E:$E,Journals!E$1) -> 68 | F2: =+COUNTIFS(Results!$F:$F,Journals!$A2,Results!$E:$E,Journals!F$1) -> 98 | G2: =+COUNTIFS(Results!$F:$F,Journals!$A2,Results!$E:$E,Journals!G$1) -> 18 | H2: =+SUM(B2:G2) -> 307
A3: Accounting Review | B3: =+COUNTIFS(Results!$F:$F,Journals!$A3,Results!$E:$E,Journals!B$1) -> 85 | C3: =+COUNTIFS(Results!$F:$F,Journals!$A3,Results!$E:$E,Journals!C$1) -> 84 | D3: =+COUNTIFS(Results!$F:$F,Journals!$A3,Results!$E:$E,Journals!D$1) -> 132 | E3: =+COUNTIFS(Results!$F:$F,Journals!$A3,Results!$E:$E,Journals!E$1) -> 102 | F3: =+COUNTIFS(Results!$F:$F,Journals!$A3,Results!$E:$E,Journals!F$1) -> 84 | G3: =+COUNTIFS(Results!$F:$F,Journals!$A3,Results!$E:$E,Journals!G$1) -> 18 | H3: =+SUM(B3:G3) -> 505
A4: Contemporary Accounting Research | B4: =+COUNTIFS(Results!$F:$F,Journals!$A4,Results!$E:$E,Journals!B$1) -> 95 | C4: =+COUNTIFS(Results!$F:$F,Journals!$A4,Results!$E:$E,Journals!C$1) -> 84 | D4: =+COUNTIFS(Results!$F:$F,Journals!$A4,Results!$E:$E,Journals!D$1) -> 87 | E4: =+COUNTIFS(Results!$F:$F,Journals!$A4,Results!$E:$E,Journals!E$1) -> 82 | F4: =+COUNTIFS(Results!$F:$F,Journals!$A4,Results!$E:$E,Journals!F$1) -> 95 | G4: =+COUNTIFS(Results!$F:$F,Journals!$A4,Results!$E:$E,Journals!G$1) -> 29 | H4: =+SUM(B4:G4) -> 472
A5: Accounting, Organizations and Society | B5: =+COUNTIFS(Results!$F:$F,Journals!$A5,Results!$E:$E,Journals!B$1) -> 35 | C5: =+COUNTIFS(Results!$F:$F,Journals!$A5,Results!$E:$E,Journals!C$1) -> 32 | D5: =+COUNTIFS(Results!$F:$F,Journals!$A5,Results!$E:$E,Journals!D$1) -> 34 | E5: =+COUNTIFS(Results!$F:$F,Journals!$A5,Results!$E:$E,Journals!E$1) -> 43 | F5: =+COUNTIFS(Results!$F:$F,Journals!$A5,Results!$E:$E,Journals!F$1) -> 23 | G5: =+COUNTIFS(Results!$F:$F,Journals!$A5,Results!$E:$E,Journals!G$1) -> 11 | H5: =+SUM(B5:G5) -> 178
A6: Journal of Accounting and Economics | B6: =+COUNTIFS(Results!$F:$F,Journals!$A6,Results!$E:$E,Journals!B$1) -> 50 | C6: =+COUNTIFS(Results!$F:$F,Journals!$A6,Results!$E:$E,Journals!C$1) -> 48 | D6: =+COUNTIFS(Results!$F:$F,Journals!$A6,Results!$E:$E,Journals!D$1) -> 48 | E6: =+COUNTIFS(Results!$F:$F,Journals!$A6,Results!$E:$E,Journals!E$1) -> 52 | F6: =+COUNTIFS(Results!$F:$F,Journals!$A6,Results!$E:$E,Journals!F$1) -> 61 | G6: =+COUNTIFS(Results!$F:$F,Journals!$A6,Results!$E:$E,Journals!G$1) -> 25 | H6: =+SUM(B6:G6) -> 284
A7: Journal of Accounting Research | B7: =+COUNTIFS(Results!$F:$F,Journals!$A7,Results!$E:$E,Journals!B$1) -> 40 | C7: =+COUNTIFS(Results!$F:$F,Journals!$A7,Results!$E:$E,Journals!C$1) -> 45 | D7: =+COUNTIFS(Results!$F:$F,Journals!$A7,Results!$E:$E,Journals!D$1) -> 40 | E7: =+COUNTIFS(Results!$F:$F,Journals!$A7,Results!$E:$E,Journals!E$1) -> 47 | F7: =+COUNTIFS(Results!$F:$F,Journals!$A7,Results!$E:$E,Journals!F$1) -> 61 | G7: =+COUNTIFS(Results!$F:$F,Journals!$A7,Results!$E:$E,Journals!G$1) -> 22 | H7: =+SUM(B7:G7) -> 255
A8: Review of Accounting Studies | B8: =+COUNTIFS(Results!$F:$F,Journals!$A8,Results!$E:$E,Journals!B$1) -> 39 | C8: =+COUNTIFS(Results!$F:$F,Journals!$A8,Results!$E:$E,Journals!C$1) -> 40 | D8: =+COUNTIFS(Results!$F:$F,Journals!$A8,Results!$E:$E,Journals!D$1) -> 70 | E8: =+COUNTIFS(Results!$F:$F,Journals!$A8,Results!$E:$E,Journals!E$1) -> 100 | F8: =+COUNTIFS(Results!$F:$F,Journals!$A8,Results!$E:$E,Journals!F$1) -> 103 | G8: =+COUNTIFS(Results!$F:$F,Journals!$A8,Results!$E:$E,Journals!G$1) -> 7 | H8: =+SUM(B8:G8) -> 359
A9: Management Accounting Research | B9: =+COUNTIFS(Results!$F:$F,Journals!$A9,Results!$E:$E,Journals!B$1) -> 16 | C9: =+COUNTIFS(Results!$F:$F,Journals!$A9,Results!$E:$E,Journals!C$1) -> 16 | D9: =+COUNTIFS(Results!$F:$F,Journals!$A9,Results!$E:$E,Journals!D$1) -> 14 | E9: =+COUNTIFS(Results!$F:$F,Journals!$A9,Results!$E:$E,Journals!E$1) -> 14 | F9: =+COUNTIFS(Results!$F:$F,Journals!$A9,Results!$E:$E,Journals!F$1) -> 17 | G9: =+COUNTIFS(Results!$F:$F,Journals!$A9,Results!$E:$E,Journals!G$1) -> 6 | H9: =+SUM(B9:G9) -> 83
A10: Journal of Management Accounting Research | B10: =+COUNTIFS(Results!$F:$F,Journals!$A10,Results!$E:$E,Journals!B$1) -> 29 | C10: =+COUNTIFS(Results!$F:$F,Journals!$A10,Results!$E:$E,Journals!C$1) -> 29 | D10: =+COUNTIFS(Results!$F:$F,Journals!$A10,Results!$E:$E,Journals!D$1) -> 25 | E10: =+COUNTIFS(Results!$F:$F,Journals!$A10,Results!$E:$E,Journals!E$1) -> 29 | F10: =+COUNTIFS(Results!$F:$F,Journals!$A10,Results!$E:$E,Journals!F$1) -> 24 | G10: =+COUNTIFS(Results!$F:$F,Journals!$A10,Results!$E:$E,Journals!G$1) -> 8 | H10: =+SUM(B10:G10) -> 144
A11: Journal of Management Control | B11: =+COUNTIFS(Results!$F:$F,Journals!$A11,Results!$E:$E,Journals!B$1) -> 17 | C11: =+COUNTIFS(Results!$F:$F,Journals!$A11,Results!$E:$E,Journals!C$1) -> 16 | D11: =+COUNTIFS(Results!$F:$F,Journals!$A11,Results!$E:$E,Journals!D$1) -> 15 | E11: =+COUNTIFS(Results!$F:$F,Journals!$A11,Results!$E:$E,Journals!E$1) -> 18 | F11: =+COUNTIFS(Results!$F:$F,Journals!$A11,Results!$E:$E,Journals!F$1) -> 21 | G11: =+COUNTIFS(Results!$F:$F,Journals!$A11,Results!$E:$E,Journals!G$1) -> 1 | H11: =+SUM(B11:G11) -> 88
A12: Total | B12: =+SUM(B2:B11) -> 443 | C12: =+SUM(C2:C11) -> 436 | D12: =+SUM(D2:D11) -> 509 | E12: =+SUM(E2:E11) -> 555 | F12: =+SUM(F2:F11) -> 587 | G12: =+SUM(G2:G11) -> 145 | H12: =+SUM(H2:H11) -> 2675
A17: Source: | B17: https://www.scopus.com/sources.uri
